{
  "source_file": "public/data/exams/113-1/medicine-5.json",
  "dataset_id": "113-1_medicine-5",
  "merge": false,
  "update_file_count": 8,
  "question_count": 80,
  "merged_question_numbers": [],
  "manual_review": [
    {
      "question_number": 32,
      "notes": [
        "Q32 選項 B 使用「臍動脈」描述 Cruveilhier-Baumgarten murmur，常規應為臍靜脈/臍旁靜脈，建議人工確認題目文字。"
      ]
    },
    {
      "question_number": 35,
      "notes": [
        "Q35 影像描述 peripheral enhancement with centripetal progression 典型較像 hemangioma，但官方答案為 liver cell adenoma，建議人工確認。"
      ]
    },
    {
      "question_number": 69,
      "notes": [
        "Q69 官方答案為 A，但 A 敘述符合常見 Peyronie's disease 病因假說，建議人工複核官方答案或題目文字。"
      ]
    },
    {
      "question_number": 75,
      "notes": [
        "Q75 官方答案為 A，但男性通常是術後尿滯留風險因子，建議人工複核題意與官方答案。"
      ]
    }
  ],
  "errors": []
}
