[
  {
    "question_id": "110-2_medicine-5_051",
    "category": "????",
    "category_confidence": "high",
    "key_point": "Gasless laparoscopy ????????????????????????",
    "explanation": "??????\n??????????????????????????????????????\n\n??????\n- A. ???????????????\n- B. ??????????????????????????\n- C. ???????????????????\n- D. ????????????????????????????\n\n??????\nGasless laparoscopy ????????????????????????",
    "flashcard_front": "??? / gasless / ?? / ????",
    "flashcard_back": "???????????????gasless ??????",
    "flashcard_summary": "gasless laparoscopy / ???? -> ??????"
  },
  {
    "question_id": "110-2_medicine-5_052",
    "category": "????",
    "category_confidence": "high",
    "key_point": "??????????????????? crossed hands ???? port ?????",
    "explanation": "??????\nPort placement ??? triangulation????????????????????????????????\n\n??????\n- A. ?? trocar ????? 10 cm ????????\n- B. ?????????????????????\n- C. ??????????????\n- D. ??????????????????\n\n??????\n??????????????????? crossed hands ???? port ?????",
    "flashcard_front": "lap port placement / triangulation / 10 cm / crossed hands",
    "flashcard_back": "?? port ?????????????????",
    "flashcard_summary": "????? / crossed hands -> port ????"
  },
  {
    "question_id": "110-2_medicine-5_053",
    "category": "??",
    "category_confidence": "high",
    "key_point": "???????????????????????????????",
    "explanation": "??????\n????????????????????????????????????????\n\n??????\n- A. ???????????????? carpal tunnel syndrome?\n- B. ??????????????????????\n- C. ??????????? dermatomal/radicular pattern?\n- D. ???????????????????????\n\n??????\n???????????????????????????????",
    "flashcard_front": "CTS / median nerve / ???? / ????",
    "flashcard_back": "????????????????????",
    "flashcard_summary": "????? / ?????? -> carpal tunnel syndrome"
  },
  {
    "question_id": "110-2_medicine-5_054",
    "category": "??",
    "category_confidence": "high",
    "key_point": "??????????????????",
    "explanation": "??????\n???????????????????????????????\n\n??????\n- A. ?????????????????\n- B. ??????????????????\n- C. ??????????????????\n- D. C4 ???????????????\n\n??????\n??????????????????",
    "flashcard_front": "??? / median nerve / ????? / ??",
    "flashcard_back": "CTS ????? median nerve?",
    "flashcard_summary": "?????? / ???? -> ????"
  },
  {
    "question_id": "110-2_medicine-5_055",
    "category": "??",
    "category_confidence": "high",
    "key_point": "Phalen test ?????????????????????????",
    "explanation": "??????\nPhalen test ? Tinel sign ??? CTS ???????????? cubital tunnel?Spurling ???????\n\n??????\n- A. ???????????????????? CTS?\n- B. ???????????????\n- C. Phalen test ???????????\n- D. Spurling test ?????????\n\n??????\nPhalen test ?????????????????????????",
    "flashcard_front": "Phalen test / CTS / wrist flexion / median nerve",
    "flashcard_back": "CTS ????? Phalen/Tinel?Spurling ????",
    "flashcard_summary": "??? / Phalen test -> ????????"
  },
  {
    "question_id": "110-2_medicine-5_056",
    "category": "??",
    "category_confidence": "high",
    "key_point": "Stuck-on appearance ????????????????",
    "explanation": "??????\n????????????????????????????????????????????? Codman triangle/??????\n\n??????\n- A. ????????? radiation-induced osteosarcoma????\n- B. stuck-on appearance ?? parosteal osteosarcoma??? periosteal???????\n- C. ABC ?? telangiectatic osteosarcoma ????????\n- D. Parosteal osteosarcoma ?????????????????\n\n??????\nStuck-on appearance ????????????????",
    "flashcard_front": "osteosarcoma / parosteal / stuck-on / periosteal",
    "flashcard_back": "Stuck-on ??? parosteal osteosarcoma?",
    "flashcard_summary": "stuck-on appearance / ??? -> parosteal??? periosteal"
  },
  {
    "question_id": "110-2_medicine-5_057",
    "category": "??",
    "category_confidence": "high",
    "key_point": "?????????????????????????????",
    "explanation": "??????\n???????????? rhabdomyolysis???????????????????????????????\n\n??????\n- A. ???????????????????????\n- B. ?????????????????????????\n- C. 5P ??????????????????\n- D. ????????? 30 mmHg ??????\n\n??????\n?????????????????????????????",
    "flashcard_front": "crush injury / rhabdomyolysis / aggressive fluids / compartment syndrome",
    "flashcard_back": "????????????????????",
    "flashcard_summary": "????? / ?? -> ???????"
  },
  {
    "question_id": "110-2_medicine-5_058",
    "category": "??",
    "category_confidence": "high",
    "key_point": "Bennett fracture ??????????????????????????",
    "explanation": "??????\nBennett fracture ??? CMC ?????????????????????????????? APL ????????\n\n??????\n- A. ECRB ?????????? Bennett fracture ?????\n- B. ECRL ???????????????\n- C. EPL ????????????\n- D. Abductor pollicis longus ???????????\n\n??????\nBennett fracture ??????????????????????????",
    "flashcard_front": "Bennett fracture / first metacarpal base / APL / CMC dislocation",
    "flashcard_back": "Bennett fracture ???????? APL ???",
    "flashcard_summary": "Bennett / ???? -> abductor pollicis longus"
  },
  {
    "question_id": "110-2_medicine-5_059",
    "category": "??",
    "category_confidence": "high",
    "key_point": "Kim test ???????????apprehension test ?? anterior instability?",
    "explanation": "??????\n????????????????Anterior apprehension/relocation ??????posterior jerk/Kim test ??????sulcus sign ? inferior/multidirectional?\n\n??????\n- A. Jahnke test ???? anterior instability ?????\n- B. Apprehension test ???? anterior instability??? posterior?\n- C. Sulcus test ???? inferior ? multidirectional instability?\n- D. Kim test ?? posterior instability????\n\n??????\nKim test ???????????apprehension test ?? anterior instability?",
    "flashcard_front": "shoulder instability / Kim test / posterior / apprehension anterior",
    "flashcard_back": "?????????apprehension ???Kim ???",
    "flashcard_summary": "Kim test / shoulder -> posterior instability"
  },
  {
    "question_id": "110-2_medicine-5_060",
    "category": "??",
    "category_confidence": "high",
    "key_point": "???????????????????????????",
    "explanation": "??????\nCongenital pseudarthrosis of tibia ???????? bowing?????????????????????\n\n??????\n- A. ????????????????????????????\n- B. ???????????????????\n- C. ????????????\n- D. ??????????\n\n??????\n???????????????????????????",
    "flashcard_front": "congenital tibial pseudarthrosis / anterolateral bowing / NF1 / fracture",
    "flashcard_back": "????????????? congenital pseudarthrosis?",
    "flashcard_summary": "????? / ???? -> ???"
  }
]
