[
  {
    "id": "110-1_medicine-4_071",
    "key_point": "兒童語言發育與發育障礙的診斷特徵。",
    "explanation": "【題幹解析】\n本題題幹為「有關兒童發展之敘述,下列何者正確?\n 1大多數兒童在1歲時已能發出近似語言、但不若語言清楚的聲音\n 2大多數輕度智能障礙的兒童在5歲之前能被診斷出來\n 3大多數兒童在2歲時已能對簡單指示如「把球給我」有合宜反應\n 4特定學習障礙症中的書寫障礙(specific learning disorder with impairment in written expression)是因為智能\n 障礙所致」。解題時先辨認題目要問的是最符合題幹線索的正確選項，再把關鍵字連回小兒科的核心知識。本題答案為 A。既有解析重點如下：【題幹解析】\n本題題幹為「有關兒童發展之敘述,下列何者正確?\n 1大多數兒童在1歲時已能發出近似語言、但不若語言清楚的聲音\n 2大多數輕度智能障礙的兒童在5歲之前能被診斷出來\n 3大多數兒童在2歲時已能對簡單指示如「把球給我」有合宜反應\n 4特定學習障礙症中的書寫障礙(specific learning disorder with impairment in written expression)是因為智能\n 障礙所致」。解題時先辨認題目要問的是最符合題幹線索的正確選項，再把關鍵字連回小兒科的核心知識。本題答案為 A。既有解析重點如下：大多數嬰幼兒在 1 歲左右能發出類似語言的嘟噥聲或模仿單字 (1)；在 2 歲大時已具備良好的單步理解力，能對簡單指令如「把球給我」做出適當反應 (3)，故 (1)(3) 敘述正確，選 (A)。輕度智能障礙兒童在學齡前（5歲前）多無明顯異常，通常在入學後面臨學業挑戰時才被診斷出來；而特定學習障礙症（如書寫障礙）的診斷前提必須排除智能障礙，即患者必須具備正常智力。\n\nA.13大多數嬰幼兒在 1 歲左右能發出類似語言的嘟噥聲或模仿單字 (1)；在 2 歲大時已具備良好的單步理解力，能對簡單指令如「把球給我」做出適當反應 (3)，故 (1)(3) 敘述正確，選 (A)。輕度智能障礙兒童在學齡前（5歲前）多無明顯異常，通常在入學後面臨學業挑戰時才被診斷出來；而特定學習障礙症（如書寫障礙）的診斷前?\nB.23兒童語言發育與發育障礙的診斷特徵。\nC.24兒童語言發育與發育障礙的診斷特徵。\nD.34兒童語言發育與發育障礙的診斷特徵。\n\n兒童語言發育與發育障礙的診斷特徵。\n\n【選項詳解】\n- A. 此選項為正確答案，最符合題幹線索與核心考點。選項內容為「13」。它能把題幹中的關鍵資訊連回最合適的診斷、機轉、檢查或處置。本題可用「兒童語言發育與發育障礙的診斷特徵。」作為判斷主軸；對照原始解析重點：大多數嬰幼兒在 1 歲左右能發出類似語言的嘟噥聲或模仿單字 (1)；在 2 歲大時已具備良好的單步理解力，能對簡單指令如「把球給我」做出適當反應 (3)，故 (1)(3) 敘述正確，選 (A)。輕度智能障礙兒童在學齡前（5歲前）多無明顯異常，通常在入學後面臨學業挑戰時才被診斷出來；而特定學習障礙症（如書寫障礙）的診斷前提必須排除智能障礙，即患者必須具備正常智\n- B. 此選項不是最佳答案。選項內容為「23」。雖然可能與題目主題相關，但與題幹最關鍵的線索、疾病機轉或處置優先順序不符。本題可用「兒童語言發育與發育障礙的診斷特徵。」作為判斷主軸；對照原始解析重點：大多數嬰幼兒在 1 歲左右能發出類似語言的嘟噥聲或模仿單字 (1)；在 2 歲大時已具備良好的單步理解力，能對簡單指令如「把球給我」做出適當反應 (3)，故 (1)(3) 敘述正確，選 (A)。輕度智能障礙兒童在學齡前（5歲前）多無明顯異常，通常在入學後面臨學業挑戰時才被診斷出來；而特定學習障礙症（如書寫障礙）的診斷前提必須排除智能障礙，即患者必須具備正常智\n- C. 此選項不是最佳答案。選項內容為「24」。雖然可能與題目主題相關，但與題幹最關鍵的線索、疾病機轉或處置優先順序不符。本題可用「兒童語言發育與發育障礙的診斷特徵。」作為判斷主軸；對照原始解析重點：大多數嬰幼兒在 1 歲左右能發出類似語言的嘟噥聲或模仿單字 (1)；在 2 歲大時已具備良好的單步理解力，能對簡單指令如「把球給我」做出適當反應 (3)，故 (1)(3) 敘述正確，選 (A)。輕度智能障礙兒童在學齡前（5歲前）多無明顯異常，通常在入學後面臨學業挑戰時才被診斷出來；而特定學習障礙症（如書寫障礙）的診斷前提必須排除智能障礙，即患者必須具備正常智\n- D. 此選項不是最佳答案。選項內容為「34」。雖然可能與題目主題相關，但與題幹最關鍵的線索、疾病機轉或處置優先順序不符。本題可用「兒童語言發育與發育障礙的診斷特徵。」作為判斷主軸；對照原始解析重點：大多數嬰幼兒在 1 歲左右能發出類似語言的嘟噥聲或模仿單字 (1)；在 2 歲大時已具備良好的單步理解力，能對簡單指令如「把球給我」做出適當反應 (3)，故 (1)(3) 敘述正確，選 (A)。輕度智能障礙兒童在學齡前（5歲前）多無明顯異常，通常在入學後面臨學業挑戰時才被診斷出來；而特定學習障礙症（如書寫障礙）的診斷前提必須排除智能障礙，即患者必須具備正常智\n\n【核心考點】\n本題核心在於：兒童語言發育與發育障礙的診斷特徵。備考時建議先判斷題型是否為反向題，再用題幹關鍵字定位疾病、機轉、檢查或治療原則，最後逐項檢查選項敘述是否與該核心概念一致。\n\n【選項詳解】\n- A. 此選項為正確答案，最符合題幹線索與核心考點。選項內容為「13」。它能把題幹中的關鍵資訊連回最合適的診斷、機轉、檢查或處置。本題可用「兒童語言發育與發育障礙的診斷特徵。」作為判斷主軸；對照原始解析重點：【題幹解析】\n本題題幹為「有關兒童發展之敘述,下列何者正確?\n 1大多數兒童在1歲時已能發出近似語言、但不若語言清楚的聲音\n 2大多數輕度智能障礙的兒童在5歲之前能被診斷出來\n 3大多數兒童在2歲時已能對簡單指示如「把球給我」有合宜反應\n 4特定學習障礙症中的書寫障礙(specific learning disorder with impairment in\n- B. 此選項不是最佳答案。選項內容為「23」。雖然可能與題目主題相關，但與題幹最關鍵的線索、疾病機轉或處置優先順序不符。本題可用「兒童語言發育與發育障礙的診斷特徵。」作為判斷主軸；對照原始解析重點：【題幹解析】\n本題題幹為「有關兒童發展之敘述,下列何者正確?\n 1大多數兒童在1歲時已能發出近似語言、但不若語言清楚的聲音\n 2大多數輕度智能障礙的兒童在5歲之前能被診斷出來\n 3大多數兒童在2歲時已能對簡單指示如「把球給我」有合宜反應\n 4特定學習障礙症中的書寫障礙(specific learning disorder with impairment in\n- C. 此選項不是最佳答案。選項內容為「24」。雖然可能與題目主題相關，但與題幹最關鍵的線索、疾病機轉或處置優先順序不符。本題可用「兒童語言發育與發育障礙的診斷特徵。」作為判斷主軸；對照原始解析重點：【題幹解析】\n本題題幹為「有關兒童發展之敘述,下列何者正確?\n 1大多數兒童在1歲時已能發出近似語言、但不若語言清楚的聲音\n 2大多數輕度智能障礙的兒童在5歲之前能被診斷出來\n 3大多數兒童在2歲時已能對簡單指示如「把球給我」有合宜反應\n 4特定學習障礙症中的書寫障礙(specific learning disorder with impairment in\n- D. 此選項不是最佳答案。選項內容為「34」。雖然可能與題目主題相關，但與題幹最關鍵的線索、疾病機轉或處置優先順序不符。本題可用「兒童語言發育與發育障礙的診斷特徵。」作為判斷主軸；對照原始解析重點：【題幹解析】\n本題題幹為「有關兒童發展之敘述,下列何者正確?\n 1大多數兒童在1歲時已能發出近似語言、但不若語言清楚的聲音\n 2大多數輕度智能障礙的兒童在5歲之前能被診斷出來\n 3大多數兒童在2歲時已能對簡單指示如「把球給我」有合宜反應\n 4特定學習障礙症中的書寫障礙(specific learning disorder with impairment in\n\n【核心考點】\n本題核心在於：兒童語言發育與發育障礙的診斷特徵。備考時建議先判斷題型是否為反向題，再用題幹關鍵字定位疾病、機轉、檢查或治療原則，最後逐項檢查選項敘述是否與該核心概念一致。",
    "flashcard_front": "兒童發育 / 1歲語言能力 / 2歲簡單指令 / 輕度智障診斷年齡 / 特定學習障礙智商",
    "flashcard_back": "1歲能發嘟噥聲，2歲能遵從單步指令；輕度智障多在入學後診斷，學習障礙者智商必須正常。",
    "flashcard_summary": "兒童發育 / 1歲語言能力 / 2歲簡單指令 / 輕度智障診斷年齡 / 特定學習障礙智商 -> 1歲能發嘟噥聲，2歲能遵從單步指令；輕度智障多在入學後診斷，學習障礙者智商必須正常。",
    "category": "小兒科",
    "category_confidence": "high"
  },
  {
    "id": "110-1_medicine-4_072",
    "key_point": "注意力不足/過動症 (ADHD) 的共病特徵。",
    "explanation": "【題幹解析】\n本題題幹為「有關注意力不足/過動症(ADHD)的共病,下列何者錯誤?」。解題時先辨認題目要問的是錯誤或不適當敘述，再把關鍵字連回精神科的核心知識。本題答案為 C。既有解析重點如下：【題幹解析】\n本題題幹為「有關注意力不足/過動症(ADHD)的共病,下列何者錯誤?」。解題時先辨認題目要問的是錯誤或不適當敘述，再把關鍵字連回精神科的核心知識。本題答案為 C。既有解析重點如下：注意力不足/過動症 (ADHD) 與特定學習障礙症 (Specific learning disorders) 具有極高的共病率（約 20-30% 的 ADHD 兒童合併學習障礙），兩者在臨床上「可以同時成立診斷」，因此選項 (C) 敘述錯誤。對立反抗症 (ODD) 是 ADHD 最常見的共病，特別見於混合型個案；ADHD 亦常合併焦慮症；且長期追蹤顯示，ADHD 患童成年後罹患雙相情緒障礙症的風險顯著高於一般人群。\n\nA.對立反抗症(oppositional defiant disorder)是ADHD最常出現的共病之一,尤其出現在混合表現型的ADHD 個案注意力不足/過動症 (ADHD) 的共病特徵。\nB.比一般人較易罹患焦慮症(anxiety disorders)注意力不足/過動症 (ADHD) 的共病特徵。\nC.ADHD診斷與特定的學習障礙症(specific learning disorders)不能同時成立注意力不足/過動症 (ADHD) 與特定學習障礙症 (Specific learning disorders) 具有極高的共病率（約 20-30% 的 ADHD 兒童合併學習障礙），兩者在臨床上「可以同時成立診斷」，因此選項 (C) 敘述錯誤。對立反抗症 (ODD) 是 ADHD 最常見的共病，特別見於混合型個案；AD?\nD.長期追蹤研究發現ADHD個案比起一般人有較高的機會罹患第一型雙相情緒障礙症(bipolar I disorders)注意力不足/過動症 (ADHD) 的共病特徵。\n\n注意力不足/過動症 (ADHD) 的共病特徵。\n\n【選項詳解】\n- A. 此選項不是本題答案，表示其敘述大致符合相關醫學概念。選項內容為「對立反抗症(oppositional defiant disorder)是ADHD最常出現的共病之一,尤其出現在混合表現型的ADHD\n 個案」。在反向題中，這類選項通常是用來確認考生是否知道正確的病理生理、診斷或處置原則。本題可用「注意力不足/過動症 (ADHD) 的共病特徵。」作為判斷主軸；對照原始解析重點：注意力不足/過動症 (ADHD) 與特定學習障礙症 (Specific learning disorders) 具有極高的共病率（約 20-30% 的 ADHD 兒童合併學習障礙），兩者在臨床上「可以同時成立診斷」，因此選項 (C) 敘述錯誤。對立反抗症 (ODD) 是 ADHD 最常見的共病，特別見於混合型個案；ADHD 亦常合併焦慮症；且長期追蹤顯示，A\n- B. 此選項不是本題答案，表示其敘述大致符合相關醫學概念。選項內容為「比一般人較易罹患焦慮症(anxiety disorders)」。在反向題中，這類選項通常是用來確認考生是否知道正確的病理生理、診斷或處置原則。本題可用「注意力不足/過動症 (ADHD) 的共病特徵。」作為判斷主軸；對照原始解析重點：注意力不足/過動症 (ADHD) 與特定學習障礙症 (Specific learning disorders) 具有極高的共病率（約 20-30% 的 ADHD 兒童合併學習障礙），兩者在臨床上「可以同時成立診斷」，因此選項 (C) 敘述錯誤。對立反抗症 (ODD) 是 ADHD 最常見的共病，特別見於混合型個案；ADHD 亦常合併焦慮症；且長期追蹤顯示，A\n- C. 此選項為本題答案，因為題目問的是錯誤或不適當的敘述。選項內容為「ADHD診斷與特定的學習障礙症(specific learning disorders)不能同時成立」。作答時要注意這類題型不是選出最典型表現，而是找出與核心概念不相符的一項。本題可用「注意力不足/過動症 (ADHD) 的共病特徵。」作為判斷主軸；對照原始解析重點：注意力不足/過動症 (ADHD) 與特定學習障礙症 (Specific learning disorders) 具有極高的共病率（約 20-30% 的 ADHD 兒童合併學習障礙），兩者在臨床上「可以同時成立診斷」，因此選項 (C) 敘述錯誤。對立反抗症 (ODD) 是 ADHD 最常見的共病，特別見於混合型個案；ADHD 亦常合併焦慮症；且長期追蹤顯示，A\n- D. 此選項不是本題答案，表示其敘述大致符合相關醫學概念。選項內容為「長期追蹤研究發現ADHD個案比起一般人有較高的機會罹患第一型雙相情緒障礙症(bipolar I disorders)」。在反向題中，這類選項通常是用來確認考生是否知道正確的病理生理、診斷或處置原則。本題可用「注意力不足/過動症 (ADHD) 的共病特徵。」作為判斷主軸；對照原始解析重點：注意力不足/過動症 (ADHD) 與特定學習障礙症 (Specific learning disorders) 具有極高的共病率（約 20-30% 的 ADHD 兒童合併學習障礙），兩者在臨床上「可以同時成立診斷」，因此選項 (C) 敘述錯誤。對立反抗症 (ODD) 是 ADHD 最常見的共病，特別見於混合型個案；ADHD 亦常合併焦慮症；且長期追蹤顯示，A\n\n【核心考點】\n本題核心在於：注意力不足/過動症 (ADHD) 的共病特徵。備考時建議先判斷題型是否為反向題，再用題幹關鍵字定位疾病、機轉、檢查或治療原則，最後逐項檢查選項敘述是否與該核心概念一致。\n\n【選項詳解】\n- A. 此選項不是本題答案，表示其敘述大致符合相關醫學概念。選項內容為「對立反抗症(oppositional defiant disorder)是ADHD最常出現的共病之一,尤其出現在混合表現型的ADHD\n 個案」。在反向題中，這類選項通常是用來確認考生是否知道正確的病理生理、診斷或處置原則。本題可用「注意力不足/過動症 (ADHD) 的共病特徵。」作為判斷主軸；對照原始解析重點：【題幹解析】\n本題題幹為「有關注意力不足/過動症(ADHD)的共病,下列何者錯誤?」。解題時先辨認題目要問的是錯誤或不適當敘述，再把關鍵字連回精神科的核心知識。本題答案為 C。既有解析重點如下：注意力不足/過動症 (ADHD) 與特定學習障礙症 (Specific learning disorders) 具有極高的共病率（約 20-30% 的 ADHD 兒童\n- B. 此選項不是本題答案，表示其敘述大致符合相關醫學概念。選項內容為「比一般人較易罹患焦慮症(anxiety disorders)」。在反向題中，這類選項通常是用來確認考生是否知道正確的病理生理、診斷或處置原則。本題可用「注意力不足/過動症 (ADHD) 的共病特徵。」作為判斷主軸；對照原始解析重點：【題幹解析】\n本題題幹為「有關注意力不足/過動症(ADHD)的共病,下列何者錯誤?」。解題時先辨認題目要問的是錯誤或不適當敘述，再把關鍵字連回精神科的核心知識。本題答案為 C。既有解析重點如下：注意力不足/過動症 (ADHD) 與特定學習障礙症 (Specific learning disorders) 具有極高的共病率（約 20-30% 的 ADHD 兒童\n- C. 此選項為本題答案，因為題目問的是錯誤或不適當的敘述。選項內容為「ADHD診斷與特定的學習障礙症(specific learning disorders)不能同時成立」。作答時要注意這類題型不是選出最典型表現，而是找出與核心概念不相符的一項。本題可用「注意力不足/過動症 (ADHD) 的共病特徵。」作為判斷主軸；對照原始解析重點：【題幹解析】\n本題題幹為「有關注意力不足/過動症(ADHD)的共病,下列何者錯誤?」。解題時先辨認題目要問的是錯誤或不適當敘述，再把關鍵字連回精神科的核心知識。本題答案為 C。既有解析重點如下：注意力不足/過動症 (ADHD) 與特定學習障礙症 (Specific learning disorders) 具有極高的共病率（約 20-30% 的 ADHD 兒童\n- D. 此選項不是本題答案，表示其敘述大致符合相關醫學概念。選項內容為「長期追蹤研究發現ADHD個案比起一般人有較高的機會罹患第一型雙相情緒障礙症(bipolar I disorders)」。在反向題中，這類選項通常是用來確認考生是否知道正確的病理生理、診斷或處置原則。本題可用「注意力不足/過動症 (ADHD) 的共病特徵。」作為判斷主軸；對照原始解析重點：【題幹解析】\n本題題幹為「有關注意力不足/過動症(ADHD)的共病,下列何者錯誤?」。解題時先辨認題目要問的是錯誤或不適當敘述，再把關鍵字連回精神科的核心知識。本題答案為 C。既有解析重點如下：注意力不足/過動症 (ADHD) 與特定學習障礙症 (Specific learning disorders) 具有極高的共病率（約 20-30% 的 ADHD 兒童\n\n【核心考點】\n本題核心在於：注意力不足/過動症 (ADHD) 的共病特徵。備考時建議先判斷題型是否為反向題，再用題幹關鍵字定位疾病、機轉、檢查或治療原則，最後逐項檢查選項敘述是否與該核心概念一致。",
    "flashcard_front": "ADHD (過動症) / 特定學習障礙共病 / 對立反抗症 (ODD) / 焦慮與雙相情緒症",
    "flashcard_back": "ADHD 與特定學習障礙症「可以同時診斷」，兩者常合併出現；ODD 為其最常見共病。",
    "flashcard_summary": "ADHD (過動症) / 特定學習障礙共病 / 對立反抗症 (ODD) / 焦慮與雙相情緒症 -> ADHD 與特定學習障礙症「可以同時診斷」，兩者常合併出現；ODD 為其最常見共病。",
    "category": "精神科",
    "category_confidence": "high"
  },
  {
    "id": "110-1_medicine-4_073",
    "key_point": "精神疾病患者自殺風險的評估因素。",
    "explanation": "【題幹解析】\n本題題幹為「有關於自殺的危險性(risk),下列敘述何者錯誤?」。解題時先辨認題目要問的是錯誤或不適當敘述，再把關鍵字連回精神科的核心知識。本題答案為 B。既有解析重點如下：【題幹解析】\n本題題幹為「有關於自殺的危險性(risk),下列敘述何者錯誤?」。解題時先辨認題目要問的是錯誤或不適當敘述，再把關鍵字連回精神科的核心知識。本題答案為 B。既有解析重點如下：伴有精神病症狀（Psychosis，如思覺失調症、重鬱症伴外在幻覺妄想）的個案，其自殺風險是「顯著升高」而非降低，特別是受到命令聽幻覺 (command hallucination) 唆使或處於慢性期無望感中，故選項 (B) 敘述錯誤。重鬱症與高度無望感 (hopelessness) 皆是公認的自殺高危因子；而健全的家庭關係與良好的社會支持系統則是預防自殺的重要保護因子。\n\nA.伴有嚴重憂鬱(severe depression)的個案自殺危險性較高精神疾病患者自殺風險的評估因素。\nB.伴有精神病(psychosis)的個案自殺危險性較低伴有精神病症狀（Psychosis，如思覺失調症、重鬱症伴外在幻覺妄想）的個案，其自殺風險是「顯著升高」而非降低，特別是受到命令聽幻覺 (command hallucination) 唆使或處於慢性期無望感中，故選項 (B) 敘述錯誤。重鬱症與高度無望感 (hopelessness) 皆是公認的自殺高危因子；而健全的家?\nC.伴有無望感(hopelessness)的個案自殺危險性較高精神疾病患者自殺風險的評估因素。\nD.家庭關係佳,社會支持良好的個案自殺危險性較低精神疾病患者自殺風險的評估因素。\n\n精神疾病患者自殺風險的評估因素。\n\n【選項詳解】\n- A. 此選項不是本題答案，表示其敘述大致符合相關醫學概念。選項內容為「伴有嚴重憂鬱(severe depression)的個案自殺危險性較高」。在反向題中，這類選項通常是用來確認考生是否知道正確的病理生理、診斷或處置原則。本題可用「精神疾病患者自殺風險的評估因素。」作為判斷主軸；對照原始解析重點：伴有精神病症狀（Psychosis，如思覺失調症、重鬱症伴外在幻覺妄想）的個案，其自殺風險是「顯著升高」而非降低，特別是受到命令聽幻覺 (command hallucination) 唆使或處於慢性期無望感中，故選項 (B) 敘述錯誤。重鬱症與高度無望感 (hopelessness) 皆是公認的自殺高危因子；而健全的家庭關係與良好的社會支持系統則是預防自殺的\n- B. 此選項為本題答案，因為題目問的是錯誤或不適當的敘述。選項內容為「伴有精神病(psychosis)的個案自殺危險性較低」。作答時要注意這類題型不是選出最典型表現，而是找出與核心概念不相符的一項。本題可用「精神疾病患者自殺風險的評估因素。」作為判斷主軸；對照原始解析重點：伴有精神病症狀（Psychosis，如思覺失調症、重鬱症伴外在幻覺妄想）的個案，其自殺風險是「顯著升高」而非降低，特別是受到命令聽幻覺 (command hallucination) 唆使或處於慢性期無望感中，故選項 (B) 敘述錯誤。重鬱症與高度無望感 (hopelessness) 皆是公認的自殺高危因子；而健全的家庭關係與良好的社會支持系統則是預防自殺的\n- C. 此選項不是本題答案，表示其敘述大致符合相關醫學概念。選項內容為「伴有無望感(hopelessness)的個案自殺危險性較高」。在反向題中，這類選項通常是用來確認考生是否知道正確的病理生理、診斷或處置原則。本題可用「精神疾病患者自殺風險的評估因素。」作為判斷主軸；對照原始解析重點：伴有精神病症狀（Psychosis，如思覺失調症、重鬱症伴外在幻覺妄想）的個案，其自殺風險是「顯著升高」而非降低，特別是受到命令聽幻覺 (command hallucination) 唆使或處於慢性期無望感中，故選項 (B) 敘述錯誤。重鬱症與高度無望感 (hopelessness) 皆是公認的自殺高危因子；而健全的家庭關係與良好的社會支持系統則是預防自殺的\n- D. 此選項不是本題答案，表示其敘述大致符合相關醫學概念。選項內容為「家庭關係佳,社會支持良好的個案自殺危險性較低」。在反向題中，這類選項通常是用來確認考生是否知道正確的病理生理、診斷或處置原則。本題可用「精神疾病患者自殺風險的評估因素。」作為判斷主軸；對照原始解析重點：伴有精神病症狀（Psychosis，如思覺失調症、重鬱症伴外在幻覺妄想）的個案，其自殺風險是「顯著升高」而非降低，特別是受到命令聽幻覺 (command hallucination) 唆使或處於慢性期無望感中，故選項 (B) 敘述錯誤。重鬱症與高度無望感 (hopelessness) 皆是公認的自殺高危因子；而健全的家庭關係與良好的社會支持系統則是預防自殺的\n\n【核心考點】\n本題核心在於：精神疾病患者自殺風險的評估因素。備考時建議先判斷題型是否為反向題，再用題幹關鍵字定位疾病、機轉、檢查或治療原則，最後逐項檢查選項敘述是否與該核心概念一致。\n\n【選項詳解】\n- A. 此選項不是本題答案，表示其敘述大致符合相關醫學概念。選項內容為「伴有嚴重憂鬱(severe depression)的個案自殺危險性較高」。在反向題中，這類選項通常是用來確認考生是否知道正確的病理生理、診斷或處置原則。本題可用「精神疾病患者自殺風險的評估因素。」作為判斷主軸；對照原始解析重點：【題幹解析】\n本題題幹為「有關於自殺的危險性(risk),下列敘述何者錯誤?」。解題時先辨認題目要問的是錯誤或不適當敘述，再把關鍵字連回精神科的核心知識。本題答案為 B。既有解析重點如下：伴有精神病症狀（Psychosis，如思覺失調症、重鬱症伴外在幻覺妄想）的個案，其自殺風險是「顯著升高」而非降低，特別是受到命令聽幻覺 (command hallucina\n- B. 此選項為本題答案，因為題目問的是錯誤或不適當的敘述。選項內容為「伴有精神病(psychosis)的個案自殺危險性較低」。作答時要注意這類題型不是選出最典型表現，而是找出與核心概念不相符的一項。本題可用「精神疾病患者自殺風險的評估因素。」作為判斷主軸；對照原始解析重點：【題幹解析】\n本題題幹為「有關於自殺的危險性(risk),下列敘述何者錯誤?」。解題時先辨認題目要問的是錯誤或不適當敘述，再把關鍵字連回精神科的核心知識。本題答案為 B。既有解析重點如下：伴有精神病症狀（Psychosis，如思覺失調症、重鬱症伴外在幻覺妄想）的個案，其自殺風險是「顯著升高」而非降低，特別是受到命令聽幻覺 (command hallucina\n- C. 此選項不是本題答案，表示其敘述大致符合相關醫學概念。選項內容為「伴有無望感(hopelessness)的個案自殺危險性較高」。在反向題中，這類選項通常是用來確認考生是否知道正確的病理生理、診斷或處置原則。本題可用「精神疾病患者自殺風險的評估因素。」作為判斷主軸；對照原始解析重點：【題幹解析】\n本題題幹為「有關於自殺的危險性(risk),下列敘述何者錯誤?」。解題時先辨認題目要問的是錯誤或不適當敘述，再把關鍵字連回精神科的核心知識。本題答案為 B。既有解析重點如下：伴有精神病症狀（Psychosis，如思覺失調症、重鬱症伴外在幻覺妄想）的個案，其自殺風險是「顯著升高」而非降低，特別是受到命令聽幻覺 (command hallucina\n- D. 此選項不是本題答案，表示其敘述大致符合相關醫學概念。選項內容為「家庭關係佳,社會支持良好的個案自殺危險性較低」。在反向題中，這類選項通常是用來確認考生是否知道正確的病理生理、診斷或處置原則。本題可用「精神疾病患者自殺風險的評估因素。」作為判斷主軸；對照原始解析重點：【題幹解析】\n本題題幹為「有關於自殺的危險性(risk),下列敘述何者錯誤?」。解題時先辨認題目要問的是錯誤或不適當敘述，再把關鍵字連回精神科的核心知識。本題答案為 B。既有解析重點如下：伴有精神病症狀（Psychosis，如思覺失調症、重鬱症伴外在幻覺妄想）的個案，其自殺風險是「顯著升高」而非降低，特別是受到命令聽幻覺 (command hallucina\n\n【核心考點】\n本題核心在於：精神疾病患者自殺風險的評估因素。備考時建議先判斷題型是否為反向題，再用題幹關鍵字定位疾病、機轉、檢查或治療原則，最後逐項檢查選項敘述是否與該核心概念一致。",
    "flashcard_front": "自殺風險 / 精神病症狀 (psychosis) / 憂鬱症與無望感 / 社會支持系統保護",
    "flashcard_back": "伴有精神病症狀的個案自殺風險「偏高」（如命令聽幻覺）；無望感是強烈的自殺危險因子。",
    "flashcard_summary": "自殺風險 / 精神病症狀 (psychosis) / 憂鬱症與無望感 / 社會支持系統保護 -> 伴有精神病症狀的個案自殺風險「偏高」（如命令聽幻覺）；無望感是強烈的自殺危險因子。",
    "category": "精神科",
    "category_confidence": "high"
  },
  {
    "id": "110-1_medicine-4_074",
    "key_point": "先天性氣管食道廔管 (TEF) 的診斷與臨床病理特徵。",
    "explanation": "【題幹解析】\n本題題幹為「下列關於先天性氣管食道瘻管(congenital tracheoesophageal fistula)的敘述,何者正確?」。解題時先辨認題目要問的是最符合題幹線索的正確選項，再把關鍵字連回小兒科的核心知識。本題答案為 B。既有解析重點如下：【題幹解析】\n本題題幹為「下列關於先天性氣管食道瘻管(congenital tracheoesophageal fistula)的敘述,何者正確?」。解題時先辨認題目要問的是最符合題幹線索的正確選項，再把關鍵字連回小兒科的核心知識。本題答案為 B。既有解析重點如下：診斷先天性食道閉鎖合併氣管食道廔管 (EA/TEF) 最簡單且經典的方法，是嘗試將胃管 (NG tube) 插入食道，若卡在食道盲端並在照 X 光時顯示「胃管在上縱膈腔打圈」，即可確診，故選項 (B) 正確。TEF 有高達 50% 比例會合併其他器官畸形（如 VACTERL 聯合畸形）；注入高滲透壓離子性對比劑若不慎嗆入肺部會引發嚴重肺水腫，屬臨床禁忌；且患者的存活率與早產體重及是否合併嚴重先天性心臟病密切相關，並非一律具有高存活率。\n\nA.約有十分之一會合併其他器官先天性畸形先天性氣管食道廔管 (TEF) 的診斷與臨床病理特徵。\nB.診斷可根據胃管在上縱膈腔打圈的X光片診斷先天性食道閉鎖合併氣管食道廔管 (EA/TEF) 最簡單且經典的方法，是嘗試將胃管 (NG tube) 插入食道，若卡在食道盲端並在照 X 光時顯示「胃管在上縱膈腔打圈」，即可確診，故選項 (B) 正確。TEF 有高達 50% 比例會合併其他器官畸形（如 VACTERL 聯合畸形）；注入高滲透壓離子性對比劑若不慎嗆?\nC.注入少量高滲透壓離子性對比劑對診斷氣管食道瘻管非常必要先天性氣管食道廔管 (TEF) 的診斷與臨床病理特徵。\nD.無論有無合併其他器官先天性畸形,氣管食道瘻管病患多具高存活率先天性氣管食道廔管 (TEF) 的診斷與臨床病理特徵。\n\n先天性氣管食道廔管 (TEF) 的診斷與臨床病理特徵。\n\n【選項詳解】\n- A. 此選項不是最佳答案。選項內容為「約有十分之一會合併其他器官先天性畸形」。雖然可能與題目主題相關，但與題幹最關鍵的線索、疾病機轉或處置優先順序不符。本題可用「先天性氣管食道廔管 (TEF) 的診斷與臨床病理特徵。」作為判斷主軸；對照原始解析重點：診斷先天性食道閉鎖合併氣管食道廔管 (EA/TEF) 最簡單且經典的方法，是嘗試將胃管 (NG tube) 插入食道，若卡在食道盲端並在照 X 光時顯示「胃管在上縱膈腔打圈」，即可確診，故選項 (B) 正確。TEF 有高達 50% 比例會合併其他器官畸形（如 VACTERL 聯合畸形）；注入高滲透壓離子性對比劑若不慎嗆入肺部會引發嚴重肺水腫，屬臨床禁忌；且患\n- B. 此選項為正確答案，最符合題幹線索與核心考點。選項內容為「診斷可根據胃管在上縱膈腔打圈的X光片」。它能把題幹中的關鍵資訊連回最合適的診斷、機轉、檢查或處置。本題可用「先天性氣管食道廔管 (TEF) 的診斷與臨床病理特徵。」作為判斷主軸；對照原始解析重點：診斷先天性食道閉鎖合併氣管食道廔管 (EA/TEF) 最簡單且經典的方法，是嘗試將胃管 (NG tube) 插入食道，若卡在食道盲端並在照 X 光時顯示「胃管在上縱膈腔打圈」，即可確診，故選項 (B) 正確。TEF 有高達 50% 比例會合併其他器官畸形（如 VACTERL 聯合畸形）；注入高滲透壓離子性對比劑若不慎嗆入肺部會引發嚴重肺水腫，屬臨床禁忌；且患\n- C. 此選項不是最佳答案。選項內容為「注入少量高滲透壓離子性對比劑對診斷氣管食道瘻管非常必要」。雖然可能與題目主題相關，但與題幹最關鍵的線索、疾病機轉或處置優先順序不符。本題可用「先天性氣管食道廔管 (TEF) 的診斷與臨床病理特徵。」作為判斷主軸；對照原始解析重點：診斷先天性食道閉鎖合併氣管食道廔管 (EA/TEF) 最簡單且經典的方法，是嘗試將胃管 (NG tube) 插入食道，若卡在食道盲端並在照 X 光時顯示「胃管在上縱膈腔打圈」，即可確診，故選項 (B) 正確。TEF 有高達 50% 比例會合併其他器官畸形（如 VACTERL 聯合畸形）；注入高滲透壓離子性對比劑若不慎嗆入肺部會引發嚴重肺水腫，屬臨床禁忌；且患\n- D. 此選項不是最佳答案。選項內容為「無論有無合併其他器官先天性畸形,氣管食道瘻管病患多具高存活率」。雖然可能與題目主題相關，但與題幹最關鍵的線索、疾病機轉或處置優先順序不符。本題可用「先天性氣管食道廔管 (TEF) 的診斷與臨床病理特徵。」作為判斷主軸；對照原始解析重點：診斷先天性食道閉鎖合併氣管食道廔管 (EA/TEF) 最簡單且經典的方法，是嘗試將胃管 (NG tube) 插入食道，若卡在食道盲端並在照 X 光時顯示「胃管在上縱膈腔打圈」，即可確診，故選項 (B) 正確。TEF 有高達 50% 比例會合併其他器官畸形（如 VACTERL 聯合畸形）；注入高滲透壓離子性對比劑若不慎嗆入肺部會引發嚴重肺水腫，屬臨床禁忌；且患\n\n【核心考點】\n本題核心在於：先天性氣管食道廔管 (TEF) 的診斷與臨床病理特徵。備考時建議先判斷題型是否為反向題，再用題幹關鍵字定位疾病、機轉、檢查或治療原則，最後逐項檢查選項敘述是否與該核心概念一致。\n\n【選項詳解】\n- A. 此選項不是最佳答案。選項內容為「約有十分之一會合併其他器官先天性畸形」。雖然可能與題目主題相關，但與題幹最關鍵的線索、疾病機轉或處置優先順序不符。本題可用「先天性氣管食道廔管 (TEF) 的診斷與臨床病理特徵。」作為判斷主軸；對照原始解析重點：【題幹解析】\n本題題幹為「下列關於先天性氣管食道瘻管(congenital tracheoesophageal fistula)的敘述,何者正確?」。解題時先辨認題目要問的是最符合題幹線索的正確選項，再把關鍵字連回小兒科的核心知識。本題答案為 B。既有解析重點如下：診斷先天性食道閉鎖合併氣管食道廔管 (EA/TEF) 最簡單且經典的方法，是嘗試將胃管 (NG\n- B. 此選項為正確答案，最符合題幹線索與核心考點。選項內容為「診斷可根據胃管在上縱膈腔打圈的X光片」。它能把題幹中的關鍵資訊連回最合適的診斷、機轉、檢查或處置。本題可用「先天性氣管食道廔管 (TEF) 的診斷與臨床病理特徵。」作為判斷主軸；對照原始解析重點：【題幹解析】\n本題題幹為「下列關於先天性氣管食道瘻管(congenital tracheoesophageal fistula)的敘述,何者正確?」。解題時先辨認題目要問的是最符合題幹線索的正確選項，再把關鍵字連回小兒科的核心知識。本題答案為 B。既有解析重點如下：診斷先天性食道閉鎖合併氣管食道廔管 (EA/TEF) 最簡單且經典的方法，是嘗試將胃管 (NG\n- C. 此選項不是最佳答案。選項內容為「注入少量高滲透壓離子性對比劑對診斷氣管食道瘻管非常必要」。雖然可能與題目主題相關，但與題幹最關鍵的線索、疾病機轉或處置優先順序不符。本題可用「先天性氣管食道廔管 (TEF) 的診斷與臨床病理特徵。」作為判斷主軸；對照原始解析重點：【題幹解析】\n本題題幹為「下列關於先天性氣管食道瘻管(congenital tracheoesophageal fistula)的敘述,何者正確?」。解題時先辨認題目要問的是最符合題幹線索的正確選項，再把關鍵字連回小兒科的核心知識。本題答案為 B。既有解析重點如下：診斷先天性食道閉鎖合併氣管食道廔管 (EA/TEF) 最簡單且經典的方法，是嘗試將胃管 (NG\n- D. 此選項不是最佳答案。選項內容為「無論有無合併其他器官先天性畸形,氣管食道瘻管病患多具高存活率」。雖然可能與題目主題相關，但與題幹最關鍵的線索、疾病機轉或處置優先順序不符。本題可用「先天性氣管食道廔管 (TEF) 的診斷與臨床病理特徵。」作為判斷主軸；對照原始解析重點：【題幹解析】\n本題題幹為「下列關於先天性氣管食道瘻管(congenital tracheoesophageal fistula)的敘述,何者正確?」。解題時先辨認題目要問的是最符合題幹線索的正確選項，再把關鍵字連回小兒科的核心知識。本題答案為 B。既有解析重點如下：診斷先天性食道閉鎖合併氣管食道廔管 (EA/TEF) 最簡單且經典的方法，是嘗試將胃管 (NG\n\n【核心考點】\n本題核心在於：先天性氣管食道廔管 (TEF) 的診斷與臨床病理特徵。備考時建議先判斷題型是否為反向題，再用題幹關鍵字定位疾病、機轉、檢查或治療原則，最後逐項檢查選項敘述是否與該核心概念一致。",
    "flashcard_front": "先天性氣管食道廔管 (TEF) / 胃管X光打圈 / 離子性對比劑禁忌 / VACTERL 聯合畸形",
    "flashcard_back": "TEF 可藉由胃管在上縱膈腔打圈的 X 光片確診；禁用高滲透壓離子性對比劑以防肺水腫；常合併其他畸形。",
    "flashcard_summary": "先天性氣管食道廔管 (TEF) / 胃管X光打圈 / 離子性對比劑禁忌 / VACTERL 聯合畸形 -> TEF 可藉由胃管在上縱膈腔打圈的 X 光片確診；禁用高滲透壓離子性對比劑以防肺水腫；常合併其他畸形。",
    "category": "小兒科",
    "category_confidence": "high"
  },
  {
    "id": "110-1_medicine-4_075",
    "key_point": "顱內低壓 (Intracranial hypotension) 的特徵影像與臨床表現。",
    "explanation": "【題幹解析】\n本題題幹為「26歲女性患者,主訴姿態性頭痛已經一個星期,接受磁振造影檢查,圖A是FLAIR影像,圖B是注射顯影劑後\n 的T1加權影像,下列何者是最可能的診斷?」。解題時先辨認題目要問的是最符合題幹線索的正確選項，再把關鍵字連回神經科的核心知識。本題答案為 B。既有解析重點如下：【題幹解析】\n本題題幹為「26歲女性患者,主訴姿態性頭痛已經一個星期,接受磁振造影檢查,圖A是FLAIR影像,圖B是注射顯影劑後\n 的T1加權影像,下列何者是最可能的診斷?」。解題時先辨認題目要問的是最符合題幹線索的正確選項，再把關鍵字連回神經科的核心知識。本題答案為 B。既有解析重點如下：病患的核心症狀為典型的「姿態性頭痛」（立位加重、臥位緩解），影像學上硬腦膜瀰漫性增強、硬腦膜下積水或靜脈竇膨脹，皆是自發性顱內低壓 (Intracranial hypotension) 的特徵性變化，故選 (B)。腦膜炎通常伴隨發燒與軟腦膜 (leptomeningeal) 顯影；蜘蛛網膜下腔出血主要為腦池與腦溝出現血流信號；硬腦膜下水囊常為顱內低壓的次發表現，但最根本的診斷仍是顱內低壓。\n\nA.腦膜炎(meningitis)顱內低壓 (Intracranial hypotension) 的特徵影像與臨床表現。\nB.顱內低壓(intracranial hypotension)病患的核心症狀為典型的「姿態性頭痛」（立位加重、臥位緩解），影像學上硬腦膜瀰漫性增強、硬腦膜下積水或靜脈竇膨脹，皆是自發性顱內低壓 (Intracranial hypotension) 的特徵性變化，故選 (B)。腦膜炎通常伴隨發燒與軟腦膜 (leptomeningeal) 顯影；蜘蛛網膜下腔出血主要為腦池與腦溝出現血?\nC.蜘蛛網膜下出血(subarachnoid hemorrhage)顱內低壓 (Intracranial hypotension) 的特徵影像與臨床表現。\nD.硬腦膜下水囊(subdural hygroma)顱內低壓 (Intracranial hypotension) 的特徵影像與臨床表現。\n\n顱內低壓 (Intracranial hypotension) 的特徵影像與臨床表現。\n\n【選項詳解】\n- A. 此選項不是最佳答案。選項內容為「腦膜炎(meningitis)」。雖然可能與題目主題相關，但與題幹最關鍵的線索、疾病機轉或處置優先順序不符。本題可用「顱內低壓 (Intracranial hypotension) 的特徵影像與臨床表現。」作為判斷主軸；對照原始解析重點：病患的核心症狀為典型的「姿態性頭痛」（立位加重、臥位緩解），影像學上硬腦膜瀰漫性增強、硬腦膜下積水或靜脈竇膨脹，皆是自發性顱內低壓 (Intracranial hypotension) 的特徵性變化，故選 (B)。腦膜炎通常伴隨發燒與軟腦膜 (leptomeningeal) 顯影；蜘蛛網膜下腔出血主要為腦池與腦溝出現血流信號；硬腦膜下水囊常為顱內低壓的次發表\n- B. 此選項為正確答案，最符合題幹線索與核心考點。選項內容為「顱內低壓(intracranial hypotension)」。它能把題幹中的關鍵資訊連回最合適的診斷、機轉、檢查或處置。本題可用「顱內低壓 (Intracranial hypotension) 的特徵影像與臨床表現。」作為判斷主軸；對照原始解析重點：病患的核心症狀為典型的「姿態性頭痛」（立位加重、臥位緩解），影像學上硬腦膜瀰漫性增強、硬腦膜下積水或靜脈竇膨脹，皆是自發性顱內低壓 (Intracranial hypotension) 的特徵性變化，故選 (B)。腦膜炎通常伴隨發燒與軟腦膜 (leptomeningeal) 顯影；蜘蛛網膜下腔出血主要為腦池與腦溝出現血流信號；硬腦膜下水囊常為顱內低壓的次發表\n- C. 此選項不是最佳答案。選項內容為「蜘蛛網膜下出血(subarachnoid hemorrhage)」。雖然可能與題目主題相關，但與題幹最關鍵的線索、疾病機轉或處置優先順序不符。本題可用「顱內低壓 (Intracranial hypotension) 的特徵影像與臨床表現。」作為判斷主軸；對照原始解析重點：病患的核心症狀為典型的「姿態性頭痛」（立位加重、臥位緩解），影像學上硬腦膜瀰漫性增強、硬腦膜下積水或靜脈竇膨脹，皆是自發性顱內低壓 (Intracranial hypotension) 的特徵性變化，故選 (B)。腦膜炎通常伴隨發燒與軟腦膜 (leptomeningeal) 顯影；蜘蛛網膜下腔出血主要為腦池與腦溝出現血流信號；硬腦膜下水囊常為顱內低壓的次發表\n- D. 此選項不是最佳答案。選項內容為「硬腦膜下水囊(subdural hygroma)」。雖然可能與題目主題相關，但與題幹最關鍵的線索、疾病機轉或處置優先順序不符。本題可用「顱內低壓 (Intracranial hypotension) 的特徵影像與臨床表現。」作為判斷主軸；對照原始解析重點：病患的核心症狀為典型的「姿態性頭痛」（立位加重、臥位緩解），影像學上硬腦膜瀰漫性增強、硬腦膜下積水或靜脈竇膨脹，皆是自發性顱內低壓 (Intracranial hypotension) 的特徵性變化，故選 (B)。腦膜炎通常伴隨發燒與軟腦膜 (leptomeningeal) 顯影；蜘蛛網膜下腔出血主要為腦池與腦溝出現血流信號；硬腦膜下水囊常為顱內低壓的次發表\n\n【核心考點】\n本題核心在於：顱內低壓 (Intracranial hypotension) 的特徵影像與臨床表現。備考時建議先判斷題型是否為反向題，再用題幹關鍵字定位疾病、機轉、檢查或治療原則，最後逐項檢查選項敘述是否與該核心概念一致。\n\n【選項詳解】\n- A. 此選項不是最佳答案。選項內容為「腦膜炎(meningitis)」。雖然可能與題目主題相關，但與題幹最關鍵的線索、疾病機轉或處置優先順序不符。本題可用「顱內低壓 (Intracranial hypotension) 的特徵影像與臨床表現。」作為判斷主軸；對照原始解析重點：【題幹解析】\n本題題幹為「26歲女性患者,主訴姿態性頭痛已經一個星期,接受磁振造影檢查,圖A是FLAIR影像,圖B是注射顯影劑後\n 的T1加權影像,下列何者是最可能的診斷?」。解題時先辨認題目要問的是最符合題幹線索的正確選項，再把關鍵字連回神經科的核心知識。本題答案為 B。既有解析重點如下：病患的核心症狀為典型的「姿態性頭痛」（立位加重、臥位緩解），影像學上\n- B. 此選項為正確答案，最符合題幹線索與核心考點。選項內容為「顱內低壓(intracranial hypotension)」。它能把題幹中的關鍵資訊連回最合適的診斷、機轉、檢查或處置。本題可用「顱內低壓 (Intracranial hypotension) 的特徵影像與臨床表現。」作為判斷主軸；對照原始解析重點：【題幹解析】\n本題題幹為「26歲女性患者,主訴姿態性頭痛已經一個星期,接受磁振造影檢查,圖A是FLAIR影像,圖B是注射顯影劑後\n 的T1加權影像,下列何者是最可能的診斷?」。解題時先辨認題目要問的是最符合題幹線索的正確選項，再把關鍵字連回神經科的核心知識。本題答案為 B。既有解析重點如下：病患的核心症狀為典型的「姿態性頭痛」（立位加重、臥位緩解），影像學上\n- C. 此選項不是最佳答案。選項內容為「蜘蛛網膜下出血(subarachnoid hemorrhage)」。雖然可能與題目主題相關，但與題幹最關鍵的線索、疾病機轉或處置優先順序不符。本題可用「顱內低壓 (Intracranial hypotension) 的特徵影像與臨床表現。」作為判斷主軸；對照原始解析重點：【題幹解析】\n本題題幹為「26歲女性患者,主訴姿態性頭痛已經一個星期,接受磁振造影檢查,圖A是FLAIR影像,圖B是注射顯影劑後\n 的T1加權影像,下列何者是最可能的診斷?」。解題時先辨認題目要問的是最符合題幹線索的正確選項，再把關鍵字連回神經科的核心知識。本題答案為 B。既有解析重點如下：病患的核心症狀為典型的「姿態性頭痛」（立位加重、臥位緩解），影像學上\n- D. 此選項不是最佳答案。選項內容為「硬腦膜下水囊(subdural hygroma)」。雖然可能與題目主題相關，但與題幹最關鍵的線索、疾病機轉或處置優先順序不符。本題可用「顱內低壓 (Intracranial hypotension) 的特徵影像與臨床表現。」作為判斷主軸；對照原始解析重點：【題幹解析】\n本題題幹為「26歲女性患者,主訴姿態性頭痛已經一個星期,接受磁振造影檢查,圖A是FLAIR影像,圖B是注射顯影劑後\n 的T1加權影像,下列何者是最可能的診斷?」。解題時先辨認題目要問的是最符合題幹線索的正確選項，再把關鍵字連回神經科的核心知識。本題答案為 B。既有解析重點如下：病患的核心症狀為典型的「姿態性頭痛」（立位加重、臥位緩解），影像學上\n\n【核心考點】\n本題核心在於：顱內低壓 (Intracranial hypotension) 的特徵影像與臨床表現。備考時建議先判斷題型是否為反向題，再用題幹關鍵字定位疾病、機轉、檢查或治療原則，最後逐項檢查選項敘述是否與該核心概念一致。",
    "flashcard_front": "姿態性頭痛 / 顯影劑 MRI / 硬腦膜增強 / 顱內低壓 / 臥位改善",
    "flashcard_back": "姿態性頭痛（躺下好、站立痛）伴隨硬腦膜瀰漫性增強，診斷為自發性顱內低壓。",
    "flashcard_summary": "姿態性頭痛 / 顯影劑 MRI / 硬腦膜增強 / 顱內低壓 / 臥位改善 -> 姿態性頭痛（躺下好、站立痛）伴隨硬腦膜瀰漫性增強，診斷為自發性顱內低壓。",
    "category": "神經科",
    "category_confidence": "high"
  },
  {
    "id": "110-1_medicine-4_076",
    "key_point": "兒童外傷休克與液體復甦的生理反應。",
    "explanation": "【題幹解析】\n本題題幹為「關於5歲兒童外傷(pediatric trauma)輸液的給法,何者錯誤?」。解題時先辨認題目要問的是錯誤或不適當敘述，再把關鍵字連回小兒科的核心知識。本題答案為 C。既有解析重點如下：【題幹解析】\n本題題幹為「關於5歲兒童外傷(pediatric trauma)輸液的給法,何者錯誤?」。解題時先辨認題目要問的是錯誤或不適當敘述，再把關鍵字連回小兒科的核心知識。本題答案為 C。既有解析重點如下：兒童外傷時具有極強的血管代償收縮能力，在失血量達到約 30% 至 40% 以上（失代償性休克）之前，其血壓通常仍能維持在正常範圍內，因此選項 (C) 敘述「失血量達到 20% 就會表現出低血壓」是錯誤的。在早期代償期（失血約 15-20%），病童主要表現為心搏過速、末梢冰冷及微血管充填時間延長。生理食鹽水或乳酸林格氏液的首次灌注劑量通常為 20 mL/kg；輸血（如 packed RBCs）的常規劑量為 10 mL/kg；且在無法迅速建立靜脈通路時，骨內注射 (IO) 是一種極佳且快速的輸液途徑。\n\nA.生理食鹽水一般以每公斤20 mL給與兒童外傷休克與液體復甦的生理反應。\nB.輸血量一般以每公斤10 mL給與兒童外傷休克與液體復甦的生理反應。\nC.失血量達到20%時,就會表現出低血壓兒童外傷時具有極強的血管代償收縮能力，在失血量達到約 30% 至 40% 以上（失代償性休克）之前，其血壓通常仍能維持在正常範圍內，因此選項 (C) 敘述「失血量達到 20% 就會表現出低血壓」是錯誤的。在早期代償期（失血約 15-20%），病童主要表現為心搏過速、末梢冰冷及微血管充填時間延長。生理食鹽水或乳酸林格氏液?\nD.可以骨內注射(intraosseus injection)給與輸液兒童外傷休克與液體復甦的生理反應。\n\n兒童外傷休克與液體復甦的生理反應。\n\n【選項詳解】\n- A. 此選項不是本題答案，表示其敘述大致符合相關醫學概念。選項內容為「生理食鹽水一般以每公斤20 mL給與」。在反向題中，這類選項通常是用來確認考生是否知道正確的病理生理、診斷或處置原則。本題可用「兒童外傷休克與液體復甦的生理反應。」作為判斷主軸；對照原始解析重點：兒童外傷時具有極強的血管代償收縮能力，在失血量達到約 30% 至 40% 以上（失代償性休克）之前，其血壓通常仍能維持在正常範圍內，因此選項 (C) 敘述「失血量達到 20% 就會表現出低血壓」是錯誤的。在早期代償期（失血約 15-20%），病童主要表現為心搏過速、末梢冰冷及微血管充填時間延長。生理食鹽水或乳酸林格氏液的首次灌注劑量通常為 20 mL/kg；\n- B. 此選項不是本題答案，表示其敘述大致符合相關醫學概念。選項內容為「輸血量一般以每公斤10 mL給與」。在反向題中，這類選項通常是用來確認考生是否知道正確的病理生理、診斷或處置原則。本題可用「兒童外傷休克與液體復甦的生理反應。」作為判斷主軸；對照原始解析重點：兒童外傷時具有極強的血管代償收縮能力，在失血量達到約 30% 至 40% 以上（失代償性休克）之前，其血壓通常仍能維持在正常範圍內，因此選項 (C) 敘述「失血量達到 20% 就會表現出低血壓」是錯誤的。在早期代償期（失血約 15-20%），病童主要表現為心搏過速、末梢冰冷及微血管充填時間延長。生理食鹽水或乳酸林格氏液的首次灌注劑量通常為 20 mL/kg；\n- C. 此選項為本題答案，因為題目問的是錯誤或不適當的敘述。選項內容為「失血量達到20%時,就會表現出低血壓」。作答時要注意這類題型不是選出最典型表現，而是找出與核心概念不相符的一項。本題可用「兒童外傷休克與液體復甦的生理反應。」作為判斷主軸；對照原始解析重點：兒童外傷時具有極強的血管代償收縮能力，在失血量達到約 30% 至 40% 以上（失代償性休克）之前，其血壓通常仍能維持在正常範圍內，因此選項 (C) 敘述「失血量達到 20% 就會表現出低血壓」是錯誤的。在早期代償期（失血約 15-20%），病童主要表現為心搏過速、末梢冰冷及微血管充填時間延長。生理食鹽水或乳酸林格氏液的首次灌注劑量通常為 20 mL/kg；\n- D. 此選項不是本題答案，表示其敘述大致符合相關醫學概念。選項內容為「可以骨內注射(intraosseus injection)給與輸液」。在反向題中，這類選項通常是用來確認考生是否知道正確的病理生理、診斷或處置原則。本題可用「兒童外傷休克與液體復甦的生理反應。」作為判斷主軸；對照原始解析重點：兒童外傷時具有極強的血管代償收縮能力，在失血量達到約 30% 至 40% 以上（失代償性休克）之前，其血壓通常仍能維持在正常範圍內，因此選項 (C) 敘述「失血量達到 20% 就會表現出低血壓」是錯誤的。在早期代償期（失血約 15-20%），病童主要表現為心搏過速、末梢冰冷及微血管充填時間延長。生理食鹽水或乳酸林格氏液的首次灌注劑量通常為 20 mL/kg；\n\n【核心考點】\n本題核心在於：兒童外傷休克與液體復甦的生理反應。備考時建議先判斷題型是否為反向題，再用題幹關鍵字定位疾病、機轉、檢查或治療原則，最後逐項檢查選項敘述是否與該核心概念一致。\n\n【選項詳解】\n- A. 此選項不是本題答案，表示其敘述大致符合相關醫學概念。選項內容為「生理食鹽水一般以每公斤20 mL給與」。在反向題中，這類選項通常是用來確認考生是否知道正確的病理生理、診斷或處置原則。本題可用「兒童外傷休克與液體復甦的生理反應。」作為判斷主軸；對照原始解析重點：【題幹解析】\n本題題幹為「關於5歲兒童外傷(pediatric trauma)輸液的給法,何者錯誤?」。解題時先辨認題目要問的是錯誤或不適當敘述，再把關鍵字連回小兒科的核心知識。本題答案為 C。既有解析重點如下：兒童外傷時具有極強的血管代償收縮能力，在失血量達到約 30% 至 40% 以上（失代償性休克）之前，其血壓通常仍能維持在正常範圍內，因此選項 (C)\n- B. 此選項不是本題答案，表示其敘述大致符合相關醫學概念。選項內容為「輸血量一般以每公斤10 mL給與」。在反向題中，這類選項通常是用來確認考生是否知道正確的病理生理、診斷或處置原則。本題可用「兒童外傷休克與液體復甦的生理反應。」作為判斷主軸；對照原始解析重點：【題幹解析】\n本題題幹為「關於5歲兒童外傷(pediatric trauma)輸液的給法,何者錯誤?」。解題時先辨認題目要問的是錯誤或不適當敘述，再把關鍵字連回小兒科的核心知識。本題答案為 C。既有解析重點如下：兒童外傷時具有極強的血管代償收縮能力，在失血量達到約 30% 至 40% 以上（失代償性休克）之前，其血壓通常仍能維持在正常範圍內，因此選項 (C)\n- C. 此選項為本題答案，因為題目問的是錯誤或不適當的敘述。選項內容為「失血量達到20%時,就會表現出低血壓」。作答時要注意這類題型不是選出最典型表現，而是找出與核心概念不相符的一項。本題可用「兒童外傷休克與液體復甦的生理反應。」作為判斷主軸；對照原始解析重點：【題幹解析】\n本題題幹為「關於5歲兒童外傷(pediatric trauma)輸液的給法,何者錯誤?」。解題時先辨認題目要問的是錯誤或不適當敘述，再把關鍵字連回小兒科的核心知識。本題答案為 C。既有解析重點如下：兒童外傷時具有極強的血管代償收縮能力，在失血量達到約 30% 至 40% 以上（失代償性休克）之前，其血壓通常仍能維持在正常範圍內，因此選項 (C)\n- D. 此選項不是本題答案，表示其敘述大致符合相關醫學概念。選項內容為「可以骨內注射(intraosseus injection)給與輸液」。在反向題中，這類選項通常是用來確認考生是否知道正確的病理生理、診斷或處置原則。本題可用「兒童外傷休克與液體復甦的生理反應。」作為判斷主軸；對照原始解析重點：【題幹解析】\n本題題幹為「關於5歲兒童外傷(pediatric trauma)輸液的給法,何者錯誤?」。解題時先辨認題目要問的是錯誤或不適當敘述，再把關鍵字連回小兒科的核心知識。本題答案為 C。既有解析重點如下：兒童外傷時具有極強的血管代償收縮能力，在失血量達到約 30% 至 40% 以上（失代償性休克）之前，其血壓通常仍能維持在正常範圍內，因此選項 (C)\n\n【核心考點】\n本題核心在於：兒童外傷休克與液體復甦的生理反應。備考時建議先判斷題型是否為反向題，再用題幹關鍵字定位疾病、機轉、檢查或治療原則，最後逐項檢查選項敘述是否與該核心概念一致。",
    "flashcard_front": "兒童外傷休克 / 低血壓出現時機 / 代償能力 / 生理食鹽水復甦 / 骨內注射 (IO)",
    "flashcard_back": "兒童外傷失血需達「30-40% 以上」才顯現低血壓；20% 失血多為心速加快等代償表現；補液首劑為 20 mL/kg。",
    "flashcard_summary": "兒童外傷休克 / 低血壓出現時機 / 代償能力 / 生理食鹽水復甦 / 骨內注射 (IO) -> 兒童外傷失血需達「30-40% 以上」才顯現低血壓；20% 失血多為心速加快等代償表現；補液首劑為 20 mL/kg。",
    "category": "小兒科",
    "category_confidence": "high"
  },
  {
    "id": "110-1_medicine-4_077",
    "key_point": "疥瘡藥物治療與 Lindane 的禁忌症。",
    "explanation": "【題幹解析】\n本題題幹為「有關疥瘡的治療方式,下列敘述何者錯誤?」。解題時先辨認題目要問的是錯誤或不適當敘述，再把關鍵字連回皮膚科的核心知識。本題答案為 C。既有解析重點如下：【題幹解析】\n本題題幹為「有關疥瘡的治療方式,下列敘述何者錯誤?」。解題時先辨認題目要問的是錯誤或不適當敘述，再把關鍵字連回皮膚科的核心知識。本題答案為 C。既有解析重點如下：Lindane (γ-六氯苯) 具有潛在的「中樞神經毒性」，可能經由皮膚吸收導致抽搐與癲癇發作，因此「禁用」於孕婦、授乳母親、早產兒及兩歲以下幼童，選項 (C) 敘述錯誤。Permethrin 5% cream 是目前安全性高且首選的疥瘡藥物，須全身塗抹（頸部以下至腳趾，幼兒需塗到頭面部）；疥瘡具有高度傳染性，病患的衣物需以高溫 (50-60°C 以上) 消毒，且同室親密接觸者皆須同步接受篩檢與治療；治療後皮疹引起的搔癢可給予抗組織胺或中效能類固醇緩解。\n\nA.病人接觸過的衣物皆須高溫消毒,其同室住民也需接受檢查與治療疥瘡藥物治療與 Lindane 的禁忌症。\nB.可使用藥物permethrin cream,塗抹於頸部以下的所有皮膚表面疥瘡藥物治療與 Lindane 的禁忌症。\nC.lindane lotion因為不具有神經毒,可適用於孕婦與小孩Lindane (γ-六氯苯) 具有潛在的「中樞神經毒性」，可能經由皮膚吸收導致抽搐與癲癇發作，因此「禁用」於孕婦、授乳母親、早產兒及兩歲以下幼童，選項 (C) 敘述錯誤。Permethrin 5% cream 是目前安全性高且首選的疥瘡藥物，須全身塗抹（頸部以下至腳趾，幼兒需塗到頭面部）；疥瘡具有高度傳染性，病患的衣?\nD.可使用antihistamines或局部塗抹中強度局部類固醇(mid-potency topical corticosteroid)來緩解癢的症狀疥瘡藥物治療與 Lindane 的禁忌症。\n\n疥瘡藥物治療與 Lindane 的禁忌症。\n\n【選項詳解】\n- A. 此選項不是本題答案，表示其敘述大致符合相關醫學概念。選項內容為「病人接觸過的衣物皆須高溫消毒,其同室住民也需接受檢查與治療」。在反向題中，這類選項通常是用來確認考生是否知道正確的病理生理、診斷或處置原則。本題可用「疥瘡藥物治療與 Lindane 的禁忌症。」作為判斷主軸；對照原始解析重點：Lindane (γ-六氯苯) 具有潛在的「中樞神經毒性」，可能經由皮膚吸收導致抽搐與癲癇發作，因此「禁用」於孕婦、授乳母親、早產兒及兩歲以下幼童，選項 (C) 敘述錯誤。Permethrin 5% cream 是目前安全性高且首選的疥瘡藥物，須全身塗抹（頸部以下至腳趾，幼兒需塗到頭面部）；疥瘡具有高度傳染性，病患的衣物需以高溫 (50-60°C 以上) 消\n- B. 此選項不是本題答案，表示其敘述大致符合相關醫學概念。選項內容為「可使用藥物permethrin cream,塗抹於頸部以下的所有皮膚表面」。在反向題中，這類選項通常是用來確認考生是否知道正確的病理生理、診斷或處置原則。本題可用「疥瘡藥物治療與 Lindane 的禁忌症。」作為判斷主軸；對照原始解析重點：Lindane (γ-六氯苯) 具有潛在的「中樞神經毒性」，可能經由皮膚吸收導致抽搐與癲癇發作，因此「禁用」於孕婦、授乳母親、早產兒及兩歲以下幼童，選項 (C) 敘述錯誤。Permethrin 5% cream 是目前安全性高且首選的疥瘡藥物，須全身塗抹（頸部以下至腳趾，幼兒需塗到頭面部）；疥瘡具有高度傳染性，病患的衣物需以高溫 (50-60°C 以上) 消\n- C. 此選項為本題答案，因為題目問的是錯誤或不適當的敘述。選項內容為「lindane lotion因為不具有神經毒,可適用於孕婦與小孩」。作答時要注意這類題型不是選出最典型表現，而是找出與核心概念不相符的一項。本題可用「疥瘡藥物治療與 Lindane 的禁忌症。」作為判斷主軸；對照原始解析重點：Lindane (γ-六氯苯) 具有潛在的「中樞神經毒性」，可能經由皮膚吸收導致抽搐與癲癇發作，因此「禁用」於孕婦、授乳母親、早產兒及兩歲以下幼童，選項 (C) 敘述錯誤。Permethrin 5% cream 是目前安全性高且首選的疥瘡藥物，須全身塗抹（頸部以下至腳趾，幼兒需塗到頭面部）；疥瘡具有高度傳染性，病患的衣物需以高溫 (50-60°C 以上) 消\n- D. 此選項不是本題答案，表示其敘述大致符合相關醫學概念。選項內容為「可使用antihistamines或局部塗抹中強度局部類固醇(mid-potency topical corticosteroid)來緩解癢的症狀」。在反向題中，這類選項通常是用來確認考生是否知道正確的病理生理、診斷或處置原則。本題可用「疥瘡藥物治療與 Lindane 的禁忌症。」作為判斷主軸；對照原始解析重點：Lindane (γ-六氯苯) 具有潛在的「中樞神經毒性」，可能經由皮膚吸收導致抽搐與癲癇發作，因此「禁用」於孕婦、授乳母親、早產兒及兩歲以下幼童，選項 (C) 敘述錯誤。Permethrin 5% cream 是目前安全性高且首選的疥瘡藥物，須全身塗抹（頸部以下至腳趾，幼兒需塗到頭面部）；疥瘡具有高度傳染性，病患的衣物需以高溫 (50-60°C 以上) 消\n\n【核心考點】\n本題核心在於：疥瘡藥物治療與 Lindane 的禁忌症。備考時建議先判斷題型是否為反向題，再用題幹關鍵字定位疾病、機轉、檢查或治療原則，最後逐項檢查選項敘述是否與該核心概念一致。\n\n【選項詳解】\n- A. 此選項不是本題答案，表示其敘述大致符合相關醫學概念。選項內容為「病人接觸過的衣物皆須高溫消毒,其同室住民也需接受檢查與治療」。在反向題中，這類選項通常是用來確認考生是否知道正確的病理生理、診斷或處置原則。本題可用「疥瘡藥物治療與 Lindane 的禁忌症。」作為判斷主軸；對照原始解析重點：【題幹解析】\n本題題幹為「有關疥瘡的治療方式,下列敘述何者錯誤?」。解題時先辨認題目要問的是錯誤或不適當敘述，再把關鍵字連回皮膚科的核心知識。本題答案為 C。既有解析重點如下：Lindane (γ-六氯苯) 具有潛在的「中樞神經毒性」，可能經由皮膚吸收導致抽搐與癲癇發作，因此「禁用」於孕婦、授乳母親、早產兒及兩歲以下幼童，選項 (C) 敘述錯誤。Permet\n- B. 此選項不是本題答案，表示其敘述大致符合相關醫學概念。選項內容為「可使用藥物permethrin cream,塗抹於頸部以下的所有皮膚表面」。在反向題中，這類選項通常是用來確認考生是否知道正確的病理生理、診斷或處置原則。本題可用「疥瘡藥物治療與 Lindane 的禁忌症。」作為判斷主軸；對照原始解析重點：【題幹解析】\n本題題幹為「有關疥瘡的治療方式,下列敘述何者錯誤?」。解題時先辨認題目要問的是錯誤或不適當敘述，再把關鍵字連回皮膚科的核心知識。本題答案為 C。既有解析重點如下：Lindane (γ-六氯苯) 具有潛在的「中樞神經毒性」，可能經由皮膚吸收導致抽搐與癲癇發作，因此「禁用」於孕婦、授乳母親、早產兒及兩歲以下幼童，選項 (C) 敘述錯誤。Permet\n- C. 此選項為本題答案，因為題目問的是錯誤或不適當的敘述。選項內容為「lindane lotion因為不具有神經毒,可適用於孕婦與小孩」。作答時要注意這類題型不是選出最典型表現，而是找出與核心概念不相符的一項。本題可用「疥瘡藥物治療與 Lindane 的禁忌症。」作為判斷主軸；對照原始解析重點：【題幹解析】\n本題題幹為「有關疥瘡的治療方式,下列敘述何者錯誤?」。解題時先辨認題目要問的是錯誤或不適當敘述，再把關鍵字連回皮膚科的核心知識。本題答案為 C。既有解析重點如下：Lindane (γ-六氯苯) 具有潛在的「中樞神經毒性」，可能經由皮膚吸收導致抽搐與癲癇發作，因此「禁用」於孕婦、授乳母親、早產兒及兩歲以下幼童，選項 (C) 敘述錯誤。Permet\n- D. 此選項不是本題答案，表示其敘述大致符合相關醫學概念。選項內容為「可使用antihistamines或局部塗抹中強度局部類固醇(mid-potency topical corticosteroid)來緩解癢的症狀」。在反向題中，這類選項通常是用來確認考生是否知道正確的病理生理、診斷或處置原則。本題可用「疥瘡藥物治療與 Lindane 的禁忌症。」作為判斷主軸；對照原始解析重點：【題幹解析】\n本題題幹為「有關疥瘡的治療方式,下列敘述何者錯誤?」。解題時先辨認題目要問的是錯誤或不適當敘述，再把關鍵字連回皮膚科的核心知識。本題答案為 C。既有解析重點如下：Lindane (γ-六氯苯) 具有潛在的「中樞神經毒性」，可能經由皮膚吸收導致抽搐與癲癇發作，因此「禁用」於孕婦、授乳母親、早產兒及兩歲以下幼童，選項 (C) 敘述錯誤。Permet\n\n【核心考點】\n本題核心在於：疥瘡藥物治療與 Lindane 的禁忌症。備考時建議先判斷題型是否為反向題，再用題幹關鍵字定位疾病、機轉、檢查或治療原則，最後逐項檢查選項敘述是否與該核心概念一致。",
    "flashcard_front": "疥瘡治療 / Lindane / 神經毒性 / 孕婦與兒童禁忌 / Permethrin",
    "flashcard_back": "Lindane 因具「中樞神經毒性」，禁用于孕婦、嬰幼兒；Permethrin 為目前安全首選的疥瘡塗抹藥。",
    "flashcard_summary": "疥瘡治療 / Lindane / 神經毒性 / 孕婦與兒童禁忌 / Permethrin -> Lindane 因具「中樞神經毒性」，禁用于孕婦、嬰幼兒；Permethrin 為目前安全首選的疥瘡塗抹藥。",
    "category": "皮膚科",
    "category_confidence": "high"
  },
  {
    "id": "110-1_medicine-4_078",
    "key_point": "苯二氮平類 (Benzodiazepines) 藥物的半衰期分類。",
    "explanation": "【題幹解析】\n本題題幹為「下列benzodiazepines中,何者半衰期最短?」。解題時先辨認題目要問的是最符合題幹線索的正確選項，再把關鍵字連回精神科的核心知識。本題答案為 A。既有解析重點如下：【題幹解析】\n本題題幹為「下列benzodiazepines中,何者半衰期最短?」。解題時先辨認題目要問的是最符合題幹線索的正確選項，再把關鍵字連回精神科的核心知識。本題答案為 A。既有解析重點如下：在選項所列的苯二氮平類 (BZD) 藥物中，「Midazolam」屬於超短效型藥物，半衰期僅約 1.5 至 3 小時，常作為麻醉誘導、內視鏡檢查鎮靜或急性抽搐發作的急救用藥，故選 (A)。Alprazolam（半衰期約 12 小時）與 Lorazepam（半衰期約 10-20 小時）屬於中效型 BZD；而 Diazepam 則屬於長效型 BZD（其活性代謝物半衰期可長達 30-100 小時以上）。\n\nA.midazolam在選項所列的苯二氮平類 (BZD) 藥物中，「Midazolam」屬於超短效型藥物，半衰期僅約 1.5 至 3 小時，常作為麻醉誘導、內視鏡檢查鎮靜或急性抽搐發作的急救用藥，故選 (A)。Alprazolam（半衰期約 12 小時）與 Lorazepam（半衰期約 10-20 小時）屬於中效型 BZD；而 Diazep?\nB.diazepam苯二氮平類 (Benzodiazepines) 藥物的半衰期分類。\nC.alprazolam苯二氮平類 (Benzodiazepines) 藥物的半衰期分類。\nD.lorazepam苯二氮平類 (Benzodiazepines) 藥物的半衰期分類。\n\n苯二氮平類 (Benzodiazepines) 藥物的半衰期分類。\n\n【選項詳解】\n- A. 此選項為正確答案，最符合題幹線索與核心考點。選項內容為「midazolam」。它能把題幹中的關鍵資訊連回最合適的診斷、機轉、檢查或處置。本題可用「苯二氮平類 (Benzodiazepines) 藥物的半衰期分類。」作為判斷主軸；對照原始解析重點：在選項所列的苯二氮平類 (BZD) 藥物中，「Midazolam」屬於超短效型藥物，半衰期僅約 1.5 至 3 小時，常作為麻醉誘導、內視鏡檢查鎮靜或急性抽搐發作的急救用藥，故選 (A)。Alprazolam（半衰期約 12 小時）與 Lorazepam（半衰期約 10-20 小時）屬於中效型 BZD；而 Diazepam 則屬於長效型 BZD（其活性代謝物\n- B. 此選項不是最佳答案。選項內容為「diazepam」。雖然可能與題目主題相關，但與題幹最關鍵的線索、疾病機轉或處置優先順序不符。本題可用「苯二氮平類 (Benzodiazepines) 藥物的半衰期分類。」作為判斷主軸；對照原始解析重點：在選項所列的苯二氮平類 (BZD) 藥物中，「Midazolam」屬於超短效型藥物，半衰期僅約 1.5 至 3 小時，常作為麻醉誘導、內視鏡檢查鎮靜或急性抽搐發作的急救用藥，故選 (A)。Alprazolam（半衰期約 12 小時）與 Lorazepam（半衰期約 10-20 小時）屬於中效型 BZD；而 Diazepam 則屬於長效型 BZD（其活性代謝物\n- C. 此選項不是最佳答案。選項內容為「alprazolam」。雖然可能與題目主題相關，但與題幹最關鍵的線索、疾病機轉或處置優先順序不符。本題可用「苯二氮平類 (Benzodiazepines) 藥物的半衰期分類。」作為判斷主軸；對照原始解析重點：在選項所列的苯二氮平類 (BZD) 藥物中，「Midazolam」屬於超短效型藥物，半衰期僅約 1.5 至 3 小時，常作為麻醉誘導、內視鏡檢查鎮靜或急性抽搐發作的急救用藥，故選 (A)。Alprazolam（半衰期約 12 小時）與 Lorazepam（半衰期約 10-20 小時）屬於中效型 BZD；而 Diazepam 則屬於長效型 BZD（其活性代謝物\n- D. 此選項不是最佳答案。選項內容為「lorazepam」。雖然可能與題目主題相關，但與題幹最關鍵的線索、疾病機轉或處置優先順序不符。本題可用「苯二氮平類 (Benzodiazepines) 藥物的半衰期分類。」作為判斷主軸；對照原始解析重點：在選項所列的苯二氮平類 (BZD) 藥物中，「Midazolam」屬於超短效型藥物，半衰期僅約 1.5 至 3 小時，常作為麻醉誘導、內視鏡檢查鎮靜或急性抽搐發作的急救用藥，故選 (A)。Alprazolam（半衰期約 12 小時）與 Lorazepam（半衰期約 10-20 小時）屬於中效型 BZD；而 Diazepam 則屬於長效型 BZD（其活性代謝物\n\n【核心考點】\n本題核心在於：苯二氮平類 (Benzodiazepines) 藥物的半衰期分類。備考時建議先判斷題型是否為反向題，再用題幹關鍵字定位疾病、機轉、檢查或治療原則，最後逐項檢查選項敘述是否與該核心概念一致。\n\n【選項詳解】\n- A. 此選項為正確答案，最符合題幹線索與核心考點。選項內容為「midazolam」。它能把題幹中的關鍵資訊連回最合適的診斷、機轉、檢查或處置。本題可用「苯二氮平類 (Benzodiazepines) 藥物的半衰期分類。」作為判斷主軸；對照原始解析重點：【題幹解析】\n本題題幹為「下列benzodiazepines中,何者半衰期最短?」。解題時先辨認題目要問的是最符合題幹線索的正確選項，再把關鍵字連回精神科的核心知識。本題答案為 A。既有解析重點如下：在選項所列的苯二氮平類 (BZD) 藥物中，「Midazolam」屬於超短效型藥物，半衰期僅約 1.5 至 3 小時，常作為麻醉誘導、內視鏡檢查鎮靜或急性抽搐發\n- B. 此選項不是最佳答案。選項內容為「diazepam」。雖然可能與題目主題相關，但與題幹最關鍵的線索、疾病機轉或處置優先順序不符。本題可用「苯二氮平類 (Benzodiazepines) 藥物的半衰期分類。」作為判斷主軸；對照原始解析重點：【題幹解析】\n本題題幹為「下列benzodiazepines中,何者半衰期最短?」。解題時先辨認題目要問的是最符合題幹線索的正確選項，再把關鍵字連回精神科的核心知識。本題答案為 A。既有解析重點如下：在選項所列的苯二氮平類 (BZD) 藥物中，「Midazolam」屬於超短效型藥物，半衰期僅約 1.5 至 3 小時，常作為麻醉誘導、內視鏡檢查鎮靜或急性抽搐發\n- C. 此選項不是最佳答案。選項內容為「alprazolam」。雖然可能與題目主題相關，但與題幹最關鍵的線索、疾病機轉或處置優先順序不符。本題可用「苯二氮平類 (Benzodiazepines) 藥物的半衰期分類。」作為判斷主軸；對照原始解析重點：【題幹解析】\n本題題幹為「下列benzodiazepines中,何者半衰期最短?」。解題時先辨認題目要問的是最符合題幹線索的正確選項，再把關鍵字連回精神科的核心知識。本題答案為 A。既有解析重點如下：在選項所列的苯二氮平類 (BZD) 藥物中，「Midazolam」屬於超短效型藥物，半衰期僅約 1.5 至 3 小時，常作為麻醉誘導、內視鏡檢查鎮靜或急性抽搐發\n- D. 此選項不是最佳答案。選項內容為「lorazepam」。雖然可能與題目主題相關，但與題幹最關鍵的線索、疾病機轉或處置優先順序不符。本題可用「苯二氮平類 (Benzodiazepines) 藥物的半衰期分類。」作為判斷主軸；對照原始解析重點：【題幹解析】\n本題題幹為「下列benzodiazepines中,何者半衰期最短?」。解題時先辨認題目要問的是最符合題幹線索的正確選項，再把關鍵字連回精神科的核心知識。本題答案為 A。既有解析重點如下：在選項所列的苯二氮平類 (BZD) 藥物中，「Midazolam」屬於超短效型藥物，半衰期僅約 1.5 至 3 小時，常作為麻醉誘導、內視鏡檢查鎮靜或急性抽搐發\n\n【核心考點】\n本題核心在於：苯二氮平類 (Benzodiazepines) 藥物的半衰期分類。備考時建議先判斷題型是否為反向題，再用題幹關鍵字定位疾病、機轉、檢查或治療原則，最後逐項檢查選項敘述是否與該核心概念一致。",
    "flashcard_front": "Benzodiazepines (BZD) / 半衰期最短 / Midazolam / Diazepam / Alprazolam與Lorazepam",
    "flashcard_back": "Midazolam 屬於超短效型 BZD，半衰期最短（1.5-3小時）；Diazepam 則為長效型 BZD。",
    "flashcard_summary": "Benzodiazepines (BZD) / 半衰期最短 / Midazolam / Diazepam / Alprazolam與Lorazepam -> Midazolam 屬於超短效型 BZD，半衰期最短（1.5-3小時）；Diazepam 則為長效型 BZD。",
    "category": "精神科",
    "category_confidence": "high"
  },
  {
    "id": "110-1_medicine-4_079",
    "key_point": "晚期癌症青少年病患的最佳利益與安寧共同照護。",
    "explanation": "【題幹解析】\n本題題幹為「佳佳是一個15歲的國三少女,即將參加升學考試之際被診斷出罹患一種十分罕見且預後不佳的癌症,所需的\n 化療劑量比起其他癌症高出許多,白血球數目降到很低,為避免感染入住單人病房隔離,此外常常需要接受\n 骨髓檢查以了解治療之效果。主治醫師與家長討論佳佳預後十分不樂觀,目前也無有效的治療方式,但家長\n 堅持無論如何一定要救治他們的女兒,否則就要轉院。佳佳身體狀況越來越差,常常疼痛難耐,且因為掉髮\n 所造成的外觀問題,感到極度沮喪與封閉。下列那一個是佳佳的主治醫師考量她最大利益的最好作法?」。解題時先辨認題目要問的是最符合題幹線索的正確選項，再把關鍵字連回醫學倫理與醫療決策的核心知識。本題答案為 C。既有解析重點如下：【題幹解析】\n本題題幹為「佳佳是一個15歲的國三少女,即將參加升學考試之際被診斷出罹患一種十分罕見且預後不佳的癌症,所需的\n 化療劑量比起其他癌症高出許多,白血球數目降到很低,為避免感染入住單人病房隔離,此外常常需要接受\n 骨髓檢查以了解治療之效果。主治醫師與家長討論佳佳預後十分不樂觀,目前也無有效的治療方式,但家長\n 堅持無論如何一定要救治他們的女兒,否則就要轉院。佳佳身體狀況越來越差,常常疼痛難耐,且因為掉髮\n 所造成的外觀問題,感到極度沮喪與封閉。下列那一個是佳佳的主治醫師考量她最大利益的最好作法?」。解題時先辨認題目要問的是最符合題幹線索的正確選項，再把關鍵字連回醫學倫理與醫療決策的核心知識。本題答案為 C。既有解析重點如下：針對預後極差且深受痛苦折磨的晚期癌症青少年，醫師考量其最大利益的作法應是照會安寧緩和照護團隊 (C) 進行共照，以提供積極的疼痛控制與心理諮商，改善其生活品質。一味順從家長要求繼續給予無效且具毒性的化療 (B)，或者在病患與家長未做好心理準備前就強行說服轉入安寧病房 (D)，皆不符合病患最大利益；而同意轉院 (A) 則是逃避醫療責任，無法即時緩解病患眼前的痛苦。\n\nA.同意他們轉院晚期癌症青少年病患的最佳利益與安寧共同照護。\nB.繼續給予化學治療晚期癌症青少年病患的最佳利益與安寧共同照護。\nC.照會安寧照護團隊為佳佳控制疼痛針對預後極差且深受痛苦折磨的晚期癌症青少年，醫師考量其最大利益的作法應是照會安寧緩和照護團隊 (C) 進行共照，以提供積極的疼痛控制與心理諮商，改善其生活品質。一味順從家長要求繼續給予無效且具毒性的化療 (B)，或者在病患與家長未做好心理準備前就強行說服轉入安寧病房 (D)，皆不符合病患最大利益；而同意轉院 (A) 則?\nD.說服佳佳轉到安寧病房晚期癌症青少年病患的最佳利益與安寧共同照護。\n\n晚期癌症青少年病患的最佳利益與安寧共同照護。\n\n【選項詳解】\n- A. 此選項不是最佳答案。選項內容為「同意他們轉院」。雖然可能與題目主題相關，但與題幹最關鍵的線索、疾病機轉或處置優先順序不符。本題可用「晚期癌症青少年病患的最佳利益與安寧共同照護。」作為判斷主軸；對照原始解析重點：針對預後極差且深受痛苦折磨的晚期癌症青少年，醫師考量其最大利益的作法應是照會安寧緩和照護團隊 (C) 進行共照，以提供積極的疼痛控制與心理諮商，改善其生活品質。一味順從家長要求繼續給予無效且具毒性的化療 (B)，或者在病患與家長未做好心理準備前就強行說服轉入安寧病房 (D)，皆不符合病患最大利益；而同意轉院 (A) 則是逃避醫療責任，無法即時緩解病患眼前的痛\n- B. 此選項不是最佳答案。選項內容為「繼續給予化學治療」。雖然可能與題目主題相關，但與題幹最關鍵的線索、疾病機轉或處置優先順序不符。本題可用「晚期癌症青少年病患的最佳利益與安寧共同照護。」作為判斷主軸；對照原始解析重點：針對預後極差且深受痛苦折磨的晚期癌症青少年，醫師考量其最大利益的作法應是照會安寧緩和照護團隊 (C) 進行共照，以提供積極的疼痛控制與心理諮商，改善其生活品質。一味順從家長要求繼續給予無效且具毒性的化療 (B)，或者在病患與家長未做好心理準備前就強行說服轉入安寧病房 (D)，皆不符合病患最大利益；而同意轉院 (A) 則是逃避醫療責任，無法即時緩解病患眼前的痛\n- C. 此選項為正確答案，最符合題幹線索與核心考點。選項內容為「照會安寧照護團隊為佳佳控制疼痛」。它能把題幹中的關鍵資訊連回最合適的診斷、機轉、檢查或處置。本題可用「晚期癌症青少年病患的最佳利益與安寧共同照護。」作為判斷主軸；對照原始解析重點：針對預後極差且深受痛苦折磨的晚期癌症青少年，醫師考量其最大利益的作法應是照會安寧緩和照護團隊 (C) 進行共照，以提供積極的疼痛控制與心理諮商，改善其生活品質。一味順從家長要求繼續給予無效且具毒性的化療 (B)，或者在病患與家長未做好心理準備前就強行說服轉入安寧病房 (D)，皆不符合病患最大利益；而同意轉院 (A) 則是逃避醫療責任，無法即時緩解病患眼前的痛\n- D. 此選項不是最佳答案。選項內容為「說服佳佳轉到安寧病房」。雖然可能與題目主題相關，但與題幹最關鍵的線索、疾病機轉或處置優先順序不符。本題可用「晚期癌症青少年病患的最佳利益與安寧共同照護。」作為判斷主軸；對照原始解析重點：針對預後極差且深受痛苦折磨的晚期癌症青少年，醫師考量其最大利益的作法應是照會安寧緩和照護團隊 (C) 進行共照，以提供積極的疼痛控制與心理諮商，改善其生活品質。一味順從家長要求繼續給予無效且具毒性的化療 (B)，或者在病患與家長未做好心理準備前就強行說服轉入安寧病房 (D)，皆不符合病患最大利益；而同意轉院 (A) 則是逃避醫療責任，無法即時緩解病患眼前的痛\n\n【核心考點】\n本題核心在於：晚期癌症青少年病患的最佳利益與安寧共同照護。備考時建議先判斷題型是否為反向題，再用題幹關鍵字定位疾病、機轉、檢查或治療原則，最後逐項檢查選項敘述是否與該核心概念一致。\n\n【選項詳解】\n- A. 此選項不是最佳答案。選項內容為「同意他們轉院」。雖然可能與題目主題相關，但與題幹最關鍵的線索、疾病機轉或處置優先順序不符。本題可用「晚期癌症青少年病患的最佳利益與安寧共同照護。」作為判斷主軸；對照原始解析重點：【題幹解析】\n本題題幹為「佳佳是一個15歲的國三少女,即將參加升學考試之際被診斷出罹患一種十分罕見且預後不佳的癌症,所需的\n 化療劑量比起其他癌症高出許多,白血球數目降到很低,為避免感染入住單人病房隔離,此外常常需要接受\n 骨髓檢查以了解治療之效果。主治醫師與家長討論佳佳預後十分不樂觀,目前也無有效的治療方式,但家長\n 堅持無論如何一定要救治他們的女兒,否則\n- B. 此選項不是最佳答案。選項內容為「繼續給予化學治療」。雖然可能與題目主題相關，但與題幹最關鍵的線索、疾病機轉或處置優先順序不符。本題可用「晚期癌症青少年病患的最佳利益與安寧共同照護。」作為判斷主軸；對照原始解析重點：【題幹解析】\n本題題幹為「佳佳是一個15歲的國三少女,即將參加升學考試之際被診斷出罹患一種十分罕見且預後不佳的癌症,所需的\n 化療劑量比起其他癌症高出許多,白血球數目降到很低,為避免感染入住單人病房隔離,此外常常需要接受\n 骨髓檢查以了解治療之效果。主治醫師與家長討論佳佳預後十分不樂觀,目前也無有效的治療方式,但家長\n 堅持無論如何一定要救治他們的女兒,否則\n- C. 此選項為正確答案，最符合題幹線索與核心考點。選項內容為「照會安寧照護團隊為佳佳控制疼痛」。它能把題幹中的關鍵資訊連回最合適的診斷、機轉、檢查或處置。本題可用「晚期癌症青少年病患的最佳利益與安寧共同照護。」作為判斷主軸；對照原始解析重點：【題幹解析】\n本題題幹為「佳佳是一個15歲的國三少女,即將參加升學考試之際被診斷出罹患一種十分罕見且預後不佳的癌症,所需的\n 化療劑量比起其他癌症高出許多,白血球數目降到很低,為避免感染入住單人病房隔離,此外常常需要接受\n 骨髓檢查以了解治療之效果。主治醫師與家長討論佳佳預後十分不樂觀,目前也無有效的治療方式,但家長\n 堅持無論如何一定要救治他們的女兒,否則\n- D. 此選項不是最佳答案。選項內容為「說服佳佳轉到安寧病房」。雖然可能與題目主題相關，但與題幹最關鍵的線索、疾病機轉或處置優先順序不符。本題可用「晚期癌症青少年病患的最佳利益與安寧共同照護。」作為判斷主軸；對照原始解析重點：【題幹解析】\n本題題幹為「佳佳是一個15歲的國三少女,即將參加升學考試之際被診斷出罹患一種十分罕見且預後不佳的癌症,所需的\n 化療劑量比起其他癌症高出許多,白血球數目降到很低,為避免感染入住單人病房隔離,此外常常需要接受\n 骨髓檢查以了解治療之效果。主治醫師與家長討論佳佳預後十分不樂觀,目前也無有效的治療方式,但家長\n 堅持無論如何一定要救治他們的女兒,否則\n\n【核心考點】\n本題核心在於：晚期癌症青少年病患的最佳利益與安寧共同照護。備考時建議先判斷題型是否為反向題，再用題幹關鍵字定位疾病、機轉、檢查或治療原則，最後逐項檢查選項敘述是否與該核心概念一致。",
    "flashcard_front": "晚期癌症青少年 / 疼痛難耐與沮喪 / 家長堅持無效治療 / 最佳利益 / 安寧共同照護",
    "flashcard_back": "對於晚期癌症痛苦病患，引進「安寧共同照護團隊」協助症狀控制與心理支持最符合其最大利益。",
    "flashcard_summary": "晚期癌症青少年 / 疼痛難耐與沮喪 / 家長堅持無效治療 / 最佳利益 / 安寧共同照護 -> 對於晚期癌症痛苦病患，引進「安寧共同照護團隊」協助症狀控制與心理支持最符合其最大利益。",
    "category": "醫學倫理與醫療決策",
    "category_confidence": "high"
  },
  {
    "id": "110-1_medicine-4_080",
    "key_point": "醫療保密義務的界限與例外情況。",
    "explanation": "【題幹解析】\n本題題幹為「有關隱私保密,下列何者錯誤?」。解題時先辨認題目要問的是錯誤或不適當敘述，再把關鍵字連回醫學倫理與醫療決策的核心知識。本題答案為 A。既有解析重點如下：【題幹解析】\n本題題幹為「有關隱私保密,下列何者錯誤?」。解題時先辨認題目要問的是錯誤或不適當敘述，再把關鍵字連回醫學倫理與醫療決策的核心知識。本題答案為 A。既有解析重點如下：醫療守密義務「並非絕對」，當涉及重大公共安全（如法定傳染病通報）、公共衛生、或者有明確危及第三者生命財產安全的重大緊急情況時，法律與倫理皆允許甚至強制要求醫療人員合理且適度地揭露患者資訊，因此選項 (A) 敘述「不得以任何理由洩漏」是錯誤的。在進行此類例外披露時，醫師仍應本著尊重自主原則，儘量先與病患溝通取得理解；例如診斷出開放性肺結核時，依法必須在 24 小時內通報主管機關。\n\nA.與病患有關的一切個人資訊,醫療人員都有義務保守秘密,不得以任何理由洩漏出去醫療守密義務「並非絕對」，當涉及重大公共安全（如法定傳染病通報）、公共衛生、或者有明確危及第三者生命財產安全的重大緊急情況時，法律與倫理皆允許甚至強制要求醫療人員合理且適度地揭露患者資訊，因此選項 (A) 敘述「不得以任何理由洩漏」是錯誤的。在進行此類例外披露時，醫師仍應本著尊重自主原則，儘量先與病患溝通取得理解；例如?\nB.因為某些公共衛生、公共安全的理由,或是涉及到第三者的重大利益,醫療人員可適當的違反守密義務,揭 露病患的個人資訊醫療保密義務的界限與例外情況。\nC.醫療人員因為第三者利益得在必要時揭露病患資訊,但最好還是先經過與病患的溝通,取得病患的理解與配 合醫療保密義務的界限與例外情況。\nD.當遇到如開放性肺結核的法定傳染性病案例,醫師有通報義務醫療保密義務的界限與例外情況。\n\n醫療保密義務的界限與例外情況。\n\n【選項詳解】\n- A. 此選項為本題答案，因為題目問的是錯誤或不適當的敘述。選項內容為「與病患有關的一切個人資訊,醫療人員都有義務保守秘密,不得以任何理由洩漏出去」。作答時要注意這類題型不是選出最典型表現，而是找出與核心概念不相符的一項。本題可用「醫療保密義務的界限與例外情況。」作為判斷主軸；對照原始解析重點：醫療守密義務「並非絕對」，當涉及重大公共安全（如法定傳染病通報）、公共衛生、或者有明確危及第三者生命財產安全的重大緊急情況時，法律與倫理皆允許甚至強制要求醫療人員合理且適度地揭露患者資訊，因此選項 (A) 敘述「不得以任何理由洩漏」是錯誤的。在進行此類例外披露時，醫師仍應本著尊重自主原則，儘量先與病患溝通取得理解；例如診斷出開放性肺結核時，依法必須在 24 \n- B. 此選項不是本題答案，表示其敘述大致符合相關醫學概念。選項內容為「因為某些公共衛生、公共安全的理由,或是涉及到第三者的重大利益,醫療人員可適當的違反守密義務,揭\n 露病患的個人資訊」。在反向題中，這類選項通常是用來確認考生是否知道正確的病理生理、診斷或處置原則。本題可用「醫療保密義務的界限與例外情況。」作為判斷主軸；對照原始解析重點：醫療守密義務「並非絕對」，當涉及重大公共安全（如法定傳染病通報）、公共衛生、或者有明確危及第三者生命財產安全的重大緊急情況時，法律與倫理皆允許甚至強制要求醫療人員合理且適度地揭露患者資訊，因此選項 (A) 敘述「不得以任何理由洩漏」是錯誤的。在進行此類例外披露時，醫師仍應本著尊重自主原則，儘量先與病患溝通取得理解；例如診斷出開放性肺結核時，依法必須在 24 \n- C. 此選項不是本題答案，表示其敘述大致符合相關醫學概念。選項內容為「醫療人員因為第三者利益得在必要時揭露病患資訊,但最好還是先經過與病患的溝通,取得病患的理解與配\n 合」。在反向題中，這類選項通常是用來確認考生是否知道正確的病理生理、診斷或處置原則。本題可用「醫療保密義務的界限與例外情況。」作為判斷主軸；對照原始解析重點：醫療守密義務「並非絕對」，當涉及重大公共安全（如法定傳染病通報）、公共衛生、或者有明確危及第三者生命財產安全的重大緊急情況時，法律與倫理皆允許甚至強制要求醫療人員合理且適度地揭露患者資訊，因此選項 (A) 敘述「不得以任何理由洩漏」是錯誤的。在進行此類例外披露時，醫師仍應本著尊重自主原則，儘量先與病患溝通取得理解；例如診斷出開放性肺結核時，依法必須在 24 \n- D. 此選項不是本題答案，表示其敘述大致符合相關醫學概念。選項內容為「當遇到如開放性肺結核的法定傳染性病案例,醫師有通報義務」。在反向題中，這類選項通常是用來確認考生是否知道正確的病理生理、診斷或處置原則。本題可用「醫療保密義務的界限與例外情況。」作為判斷主軸；對照原始解析重點：醫療守密義務「並非絕對」，當涉及重大公共安全（如法定傳染病通報）、公共衛生、或者有明確危及第三者生命財產安全的重大緊急情況時，法律與倫理皆允許甚至強制要求醫療人員合理且適度地揭露患者資訊，因此選項 (A) 敘述「不得以任何理由洩漏」是錯誤的。在進行此類例外披露時，醫師仍應本著尊重自主原則，儘量先與病患溝通取得理解；例如診斷出開放性肺結核時，依法必須在 24 \n\n【核心考點】\n本題核心在於：醫療保密義務的界限與例外情況。備考時建議先判斷題型是否為反向題，再用題幹關鍵字定位疾病、機轉、檢查或治療原則，最後逐項檢查選項敘述是否與該核心概念一致。\n\n【選項詳解】\n- A. 此選項為本題答案，因為題目問的是錯誤或不適當的敘述。選項內容為「與病患有關的一切個人資訊,醫療人員都有義務保守秘密,不得以任何理由洩漏出去」。作答時要注意這類題型不是選出最典型表現，而是找出與核心概念不相符的一項。本題可用「醫療保密義務的界限與例外情況。」作為判斷主軸；對照原始解析重點：【題幹解析】\n本題題幹為「有關隱私保密,下列何者錯誤?」。解題時先辨認題目要問的是錯誤或不適當敘述，再把關鍵字連回醫學倫理與醫療決策的核心知識。本題答案為 A。既有解析重點如下：醫療守密義務「並非絕對」，當涉及重大公共安全（如法定傳染病通報）、公共衛生、或者有明確危及第三者生命財產安全的重大緊急情況時，法律與倫理皆允許甚至強制要求醫療人員合理且適度地揭露患者\n- B. 此選項不是本題答案，表示其敘述大致符合相關醫學概念。選項內容為「因為某些公共衛生、公共安全的理由,或是涉及到第三者的重大利益,醫療人員可適當的違反守密義務,揭\n 露病患的個人資訊」。在反向題中，這類選項通常是用來確認考生是否知道正確的病理生理、診斷或處置原則。本題可用「醫療保密義務的界限與例外情況。」作為判斷主軸；對照原始解析重點：【題幹解析】\n本題題幹為「有關隱私保密,下列何者錯誤?」。解題時先辨認題目要問的是錯誤或不適當敘述，再把關鍵字連回醫學倫理與醫療決策的核心知識。本題答案為 A。既有解析重點如下：醫療守密義務「並非絕對」，當涉及重大公共安全（如法定傳染病通報）、公共衛生、或者有明確危及第三者生命財產安全的重大緊急情況時，法律與倫理皆允許甚至強制要求醫療人員合理且適度地揭露患者\n- C. 此選項不是本題答案，表示其敘述大致符合相關醫學概念。選項內容為「醫療人員因為第三者利益得在必要時揭露病患資訊,但最好還是先經過與病患的溝通,取得病患的理解與配\n 合」。在反向題中，這類選項通常是用來確認考生是否知道正確的病理生理、診斷或處置原則。本題可用「醫療保密義務的界限與例外情況。」作為判斷主軸；對照原始解析重點：【題幹解析】\n本題題幹為「有關隱私保密,下列何者錯誤?」。解題時先辨認題目要問的是錯誤或不適當敘述，再把關鍵字連回醫學倫理與醫療決策的核心知識。本題答案為 A。既有解析重點如下：醫療守密義務「並非絕對」，當涉及重大公共安全（如法定傳染病通報）、公共衛生、或者有明確危及第三者生命財產安全的重大緊急情況時，法律與倫理皆允許甚至強制要求醫療人員合理且適度地揭露患者\n- D. 此選項不是本題答案，表示其敘述大致符合相關醫學概念。選項內容為「當遇到如開放性肺結核的法定傳染性病案例,醫師有通報義務」。在反向題中，這類選項通常是用來確認考生是否知道正確的病理生理、診斷或處置原則。本題可用「醫療保密義務的界限與例外情況。」作為判斷主軸；對照原始解析重點：【題幹解析】\n本題題幹為「有關隱私保密,下列何者錯誤?」。解題時先辨認題目要問的是錯誤或不適當敘述，再把關鍵字連回醫學倫理與醫療決策的核心知識。本題答案為 A。既有解析重點如下：醫療守密義務「並非絕對」，當涉及重大公共安全（如法定傳染病通報）、公共衛生、或者有明確危及第三者生命財產安全的重大緊急情況時，法律與倫理皆允許甚至強制要求醫療人員合理且適度地揭露患者\n\n【核心考點】\n本題核心在於：醫療保密義務的界限與例外情況。備考時建議先判斷題型是否為反向題，再用題幹關鍵字定位疾病、機轉、檢查或治療原則，最後逐項檢查選項敘述是否與該核心概念一致。",
    "flashcard_front": "醫療守密義務 / 絕對性 vs. 相對性 / 法定傳染病通報 / 第三者重大利益 / 隱私揭露例外",
    "flashcard_back": "醫療守密義務是「相對的」而非絕對，當涉及公共安全、法定傳染病或避免第三人受害時可依法通報。",
    "flashcard_summary": "醫療守密義務 / 絕對性 vs. 相對性 / 法定傳染病通報 / 第三者重大利益 / 隱私揭露例外 -> 醫療守密義務是「相對的」而非絕對，當涉及公共安全、法定傳染病或避免第三人受害時可依法通報。",
    "category": "醫學倫理與醫療決策",
    "category_confidence": "high"
  }
]
