{
  "datasets": {
    "115_medicine-1": {
      "available_categories": [
        "生物化學",
        "解剖學",
        "胚胎及發育生物學",
        "組織學",
        "生理學",
        "其他"
      ],
      "ranges": []
    },
    "115_medicine-2": {
      "available_categories": [
        "微生物免疫學",
        "寄生蟲學",
        "藥理學",
        "病理學",
        "公共衛生學",
        "其他"
      ],
      "ranges": []
    },
    "115_medicine-3": {
      "available_categories": [
        "心臟內科",
        "胸腔內科",
        "肝膽腸胃科",
        "腎臟科",
        "新陳代謝科",
        "血液腫瘤科",
        "免疫風濕科",
        "感染科",
        "神經內科",
        "家庭醫學科",
        "急診醫學科",
        "醫學倫理與醫療決策",
        "其他"
      ],
      "ranges": []
    },
    "115_medicine-4": {
      "available_categories": [
        "小兒科",
        "皮膚科",
        "神經科",
        "精神科",
        "醫學倫理與醫療決策",
        "其他"
      ],
      "ranges": []
    },
    "115_medicine-5": {
      "available_categories": [
        "外科概論",
        "一般外科",
        "心臟外科",
        "胸腔外科",
        "大腸直腸科",
        "移植外科",
        "小兒外科",
        "整形外科",
        "神經外科",
        "骨科",
        "泌尿科",
        "其他"
      ],
      "ranges": []
    },
    "115_medicine-6": {
      "available_categories": [
        "麻醉科",
        "眼科",
        "耳鼻喉科",
        "婦產科",
        "復健科",
        "醫學倫理與醫療決策",
        "其他"
      ],
      "ranges": []
    }
  }
}
